Workbook

Sheet Program
A1: Short Code | B1: Code | C1: Description | D1: Program Coordinator | F1: Academic Year | H1: Semester | J1: Description
A2: CS | B2: 010I61 | C2: Master of Engineering – M.E in Computer Science and Engineering | D2: SNM | F2: 2026-2027 | H2: Semester - I | J2: =IF(Setup!$B$1="","",IF(Setup!$B$2="Invalid Faculty Code","Enter Valid Faculty Code",IF(C2="","",C2))) -> Master of Engineering – M.E in Computer Science and Engineering
A3: ESD | B3: 010I62 | C3: Master of Engineering - M.E in Computer Science and Engineering (Embedded Systems) | D3: BDR | F3: 2027-2028 | H3: Semester - II | J3: =IF(Setup!$B$1="","",IF(Setup!$B$2="Invalid Faculty Code","",IF(C3="","",C3))) -> Master of Engineering - M.E in Computer Science and Engineering (Embedded Systems)
A4: MVT | B4: 010I63 | C4: Master of Engineering - M.E in Electronics Engineering (Microelectronics and VLSI Technology) | D4: RM | F4: 2028-2029 | J4: =IF(Setup!$B$1="","",IF(Setup!$B$2="Invalid Faculty Code","",IF(C4="","",C4))) -> Master of Engineering - M.E in Electronics Engineering (Microelectronics and VLSI Technology)
A5: VLSI | B5: 010I64 | C5: Master of Engineering - M.E in Electronics Engineering (VLSI Design) | D5: MS | F5: 2029-2030 | J5: =IF(Setup!$B$1="","",IF(Setup!$B$2="Invalid Faculty Code","",IF(C5="","",C5))) -> Master of Engineering - M.E in Electronics Engineering (VLSI Design)
A6: AES | B6: 010I65 | C6: Master of Engineering - M.E in Computer Science and Engineering (Embedded Systems, Dual Degree Program with ESIGELEC, France) | D6: BDR | F6: 2030-2031 | J6: =IF(Setup!$B$1="","",IF(Setup!$B$2="Invalid Faculty Code","",IF(C6="","",C6))) -> Master of Engineering - M.E in Computer Science and Engineering (Embedded Systems, Dual Degree Program with ESIGELEC, France)
A7: AIML | B7: 010I66 | C7: Master of Engineering - M.E in Computer Science and Engineering (Artificial Intelligence and Machine Learning) | D7: RS | F7: 2031-2032 | J7: =IF(Setup!$B$1="","",IF(Setup!$B$2="Invalid Faculty Code","",IF(C7="","",C7))) -> Master of Engineering - M.E in Computer Science and Engineering (Artificial Intelligence and Machine Learning)
A8: BDA | B8: 010I67 | C8: Master of Engineering - M.E in Computer Science and Engineering (Big Data Analytics) | D8: RS | F8: 2032-2033 | J8: =IF(Setup!$B$1="","",IF(Setup!$B$2="Invalid Faculty Code","",IF(C8="","",C8))) -> Master of Engineering - M.E in Computer Science and Engineering (Big Data Analytics)
A9: CDC | B9: 010I68 | C9: Master of Engineering - M.E in Computer Science and Engineering (Cloud Computing) | D9: PRN | J9: =IF(Setup!$B$1="","",IF(Setup!$B$2="Invalid Faculty Code","",IF(C9="","",C9))) -> Master of Engineering - M.E in Computer Science and Engineering (Cloud Computing)
A10: CYS | B10: 010I69 | C10: Master of Engineering - M.E in Computer Science and Engineering (Cyber Security) | D10: KB | J10: =IF(Setup!$B$1="","",IF(Setup!$B$2="Invalid Faculty Code","",IF(C10="","",C10))) -> Master of Engineering - M.E in Computer Science and Engineering (Cyber Security)
J11: =IF(Setup!$B$1="","",IF(Setup!$B$2="Invalid Faculty Code","",IF(C11="","",C11)))
J12: =IF(Setup!$B$1="","",IF(Setup!$B$2="Invalid Faculty Code","",IF(C12="","",C12)))
J13: =IF(Setup!$B$1="","",IF(Setup!$B$2="Invalid Faculty Code","",IF(C13="","",C13)))
J14: =IF(Setup!$B$1="","",IF(Setup!$B$2="Invalid Faculty Code","",IF(C14="","",C14)))
J15: =IF(Setup!$B$1="","",IF(Setup!$B$2="Invalid Faculty Code","",IF(C15="","",C15)))
J16: =IF(Setup!$B$1="","",IF(Setup!$B$2="Invalid Faculty Code","",IF(C16="","",C16)))
J17: =IF(Setup!$B$1="","",IF(Setup!$B$2="Invalid Faculty Code","",IF(C17="","",C17)))
J18: =IF(Setup!$B$1="","",IF(Setup!$B$2="Invalid Faculty Code","",IF(C18="","",C18)))
J19: =IF(Setup!$B$1="","",IF(Setup!$B$2="Invalid Faculty Code","",IF(C19="","",C19)))
J20: =IF(Setup!$B$1="","",IF(Setup!$B$2="Invalid Faculty Code","",IF(C20="","",C20)))

Sheet Course
A1: Program Code | B1: Semester | C1: Course Code | D1: Course Name | E1: PO1 | F1: PO2 | G1: PO3 | H1: PO4 | I1: PO5 | J1: Sort No | K1: Short Code | L1: Subject Type | M1: Subject Class | N1: Status | P1: Active Subject | R1: PO for Mapping
A2: 010I61 | B2: I | C2: AME 5002 | D2: Applied Machine Learning | E2: * | G2: * | H2: * | J2: 1 | K2: AML | L2: Theory | M2: Core | N2: =IF(K2="","","Active") -> Active | P2: Subject Code | Q2: {=TRANSPOSE(_xlfn._xlws.FILTER($C$2:$I$600,($L$2:$L$600="Theory")*($N$2:$N$600="Active")*($A$2:$A$600=Setup!$B$7)*($C$2:$C$600=Setup!$B$8),""))} -> AME 5101
A3: 010I61 | B3: I | C3: AME 5101 | D3: Applied Linear Algebra | G3: * | H3: * | J3: 2 | K3: ALA | L3: Theory | M3: Core | N3: =IF(K3="","","Active") -> Active | P3: Subject Name | Q3: Applied Linear Algebra
A4: 010I61 | B4: I | C4: CCE 5101 | D4: Cloud Application with JAVA and Database with Java | G4: * | H4: * | I4: * | J4: 3 | K4: CAJ | L4: Theory | M4: Core | N4: =IF(K4="","","Active") -> Active | P4: PO1 | R4: {=_xlfn._xlws.FILTER($P$4:$P$8,$Q$4:$Q$8="*","")} -> PO3
A5: 010I61 | B5: I | C5: ESE 5102 | D5: Data Structures and Algorithms | G5: * | H5: * | I5: * | J5: 4 | K5: DSA | L5: Theory | M5: Core | N5: =IF(K5="","","Active") -> Active | P5: PO2 | R5: PO4
A6: 010I61 | B6: I | C6: ESE 5104 | D6: Real Time Operating Systems | G6: * | H6: * | I6: * | J6: 5 | K6: RTOS | L6: Theory | M6: Core | N6: =IF(K6="","","Active") -> Active | P6: PO3 | Q6: *
A7: 010I61 | B7: I | C7: AME 5052 | D7: Applied Machine Learning Lab | E7: * | G7: * | H7: * | J7: 6 | K7: AML Lab | L7: Lab | M7: Core | N7: =IF(K7="","","Active") -> Active | P7: PO4 | Q7: *
A8: 010I61 | B8: I | C8: AME 5151 | D8: Applied Linear Algebra Lab | G8: * | I8: * | J8: 7 | K8: ALA Lab | L8: Lab | M8: Core | N8: =IF(K8="","","Active") -> Active | P8: PO5
A9: 010I61 | B9: I | C9: CCE 5151 | D9: Cloud Application with JAVA and Database with Java Lab | G9: * | H9: * | I9: * | J9: 8 | K9: CAJ Lab | L9: Lab | M9: Core | N9: =IF(K9="","","Active") -> Active
A10: 010I61 | B10: I | C10: ESE 5152 | D10: Data Structures and Algorithms Lab | G10: * | H10: * | I10: * | J10: 9 | K10: DSA Lab | L10: Lab | M10: Core | N10: =IF(K10="","","Active") -> Active
A11: 010I61 | B11: I | C11: ESE 5154 | D11: Real Time Operating Systems Lab | G11: * | H11: * | I11: * | J11: 10 | K11: RTOS Lab | L11: Lab | M11: Core | N11: =IF(K11="","","Active") -> Active
A12: 010I61 | B12: I | C12: MPT 5100 | D12: Mini Project - I | E12: * | F12: * | G12: * | H12: * | I12: * | J12: 11 | K12: MP 1 | L12: Project | M12: Core | N12: =IF(K12="","","Active") -> Active
A13: 010I61 | B13: I | C13: PSD 5100 | D13: Professional Skill Development - I | E13: * | F13: * | J13: 12 | K13: PDS 1 | L13: Seminar | M13: Core | N13: =IF(K13="","","Active") -> Active
A14: 010I61 | B14: II | C14: AME 5202 | D14: Deep Learning | E14: * | G14: * | H14: * | J14: 13 | L14: Theory | M14: Core | N14: =IF(K14="","","Active")
A15: 010I61 | B15: II | C15: BDE 5202 | D15: Modern Databases for Big Data | E15: * | H15: * | J15: 14 | L15: Theory | M15: Core | N15: =IF(K15="","","Active") | Q15: Available Subject
A16: 010I61 | B16: II | C16: ESE 5201 | D16: Device Drivers | G16: * | I16: * | J16: 15 | L16: Theory | M16: Core | N16: =IF(K16="","","Active") | Q16: {=IF(Setup!B2="","Faculty Details Missing",_xlfn._xlws.FILTER($D$2:$D$600,($L$2:$L$600="Theory")*($N$2:$N$600="Active")*($A$2:$A$600=Setup!$B$7)*($B$2:$B$600=Setup!$B$12),""))} -> Applied Machine Learning
A17: 010I61 | B17: II | C17: AME 5204 | D17: Applied Computer Vision | G17: * | H17: * | J17: 16 | L17: Theory | M17: Ele 1 | N17: =IF(K17="","","Active") | Q17: Applied Linear Algebra
A18: 010I61 | B18: II | C18: BDE 5203 | D18: Data Engineering | E18: * | H18: * | J18: 17 | L18: Theory | M18: Ele 1 | N18: =IF(K18="","","Active") | Q18: Cloud Application with JAVA and Database with Java
A19: 010I61 | B19: II | C19: CCE 5001 | D19: DevOps for Cloud | G19: * | H19: * | I19: * | J19: 18 | L19: Theory | M19: Ele 1 | N19: =IF(K19="","","Active") | Q19: Data Structures and Algorithms
A20: 010I61 | B20: II | C20: CCE 5203 | D20: Cloud Security Essentials | G20: * | H20: * | I20: * | J20: 19 | L20: Theory | M20: Ele 1 | N20: =IF(K20="","","Active") | Q20: Real Time Operating Systems
A21: 010I61 | B21: II | C21: CYE 5202 | D21: Web Security and Secure Coding | E21: * | F21: * | I21: * | J21: 20 | L21: Theory | M21: Ele 1 | N21: =IF(K21="","","Active")
A22: 010I61 | B22: II | C22: ESE 5234 | D22: Entrepreneurship | G22: * | H22: * | J22: 21 | L22: Theory | M22: Ele 1 | N22: =IF(K22="","","Active")
A23: 010I61 | B23: II | C23: AME 5003 | D23: Principles of Natural Language Processing | G23: * | H23: * | J23: 22 | L23: Theory | M23: Ele 2 | N23: =IF(K23="","","Active")
A24: 010I61 | B24: II | C24: AME 5205 | D24: Advanced Generative AI and Agentic Systems | E24: * | G24: * | H24: * | J24: 23 | L24: Theory | M24: Ele 2 | N24: =IF(K24="","","Active")
A25: 010I61 | B25: II | C25: CCE 5241 | D25: Cloud Operations | G25: * | H25: * | I25: * | J25: 24 | L25: Theory | M25: Ele 2 | N25: =IF(K25="","","Active")
A26: 010I61 | B26: II | C26: CYE 5203 | D26: Machine Learning for Cybersecurity | G26: * | H26: * | J26: 25 | L26: Theory | M26: Ele 2 | N26: =IF(K26="","","Active")
A27: 010I61 | B27: II | C27: ESE 5244 | D27: IT Project Management | G27: * | H27: * | J27: 26 | L27: Theory | M27: Ele 2 | N27: =IF(K27="","","Active")
A28: 010I61 | B28: II | C28: AME 5252 | D28: Deep Learning Lab | E28: * | I28: * | J28: 27 | L28: Lab | M28: Core | N28: =IF(K28="","","Active")
A29: 010I61 | B29: II | C29: BDE 5252 | D29: Modern Databases for Big Data Lab | E29: * | H29: * | I29: * | J29: 28 | L29: Lab | M29: Core | N29: =IF(K29="","","Active")
A30: 010I61 | B30: II | C30: ESE 5251 | D30: Device Drivers Lab | G30: * | I30: * | J30: 29 | L30: Lab | M30: Core | N30: =IF(K30="","","Active")
A31: 010I61 | B31: II | C31: AME 5254 | D31: Applied Computer Vision Lab | G31: * | H31: * | I31: * | J31: 30 | L31: Lab | M31: Ele 1 | N31: =IF(K31="","","Active")
A32: 010I61 | B32: II | C32: BDE 5253 | D32: Data Engineering Lab | G32: * | I32: * | J32: 31 | L32: Lab | M32: Ele 1 | N32: =IF(K32="","","Active")
A33: 010I61 | B33: II | C33: CCE 5051 | D33: DevOps for Cloud Lab | G33: * | H33: * | I33: * | J33: 32 | L33: Lab | M33: Ele 1 | N33: =IF(K33="","","Active")
A34: 010I61 | B34: II | C34: CCE 5253 | D34: Cloud Security Essentials Lab | G34: * | H34: * | I34: * | J34: 33 | L34: Lab | M34: Ele 1 | N34: =IF(K34="","","Active")
A35: 010I61 | B35: II | C35: CYE 5252 | D35: Web Security and Secure Coding Lab | E35: * | F35: * | I35: * | J35: 34 | L35: Lab | M35: Ele 1 | N35: =IF(K35="","","Active")
A36: 010I61 | B36: II | C36: ESE 5284 | D36: Entrepreneurship Lab | G36: * | H36: * | J36: 35 | L36: Lab | M36: Ele 1 | N36: =IF(K36="","","Active")
A37: 010I61 | B37: II | C37: AME 5053 | D37: Principles of Natural Language Processing Lab | G37: * | I37: * | J37: 36 | L37: Lab | M37: Ele 2 | N37: =IF(K37="","","Active")
A38: 010I61 | B38: II | C38: AME 5255 | D38: Advanced Generative AI and Agentic Systems Lab | G38: * | H38: * | I38: * | J38: 37 | L38: Lab | M38: Ele 2 | N38: =IF(K38="","","Active")
A39: 010I61 | B39: II | C39: CCE 5291 | D39: Cloud Operations Lab | G39: * | H39: * | I39: * | J39: 38 | L39: Lab | M39: Ele 2 | N39: =IF(K39="","","Active")
A40: 010I61 | B40: II | C40: CYE 5253 | D40: Machine Learning for Cybersecurity Lab | G40: * | H40: * | I40: * | J40: 39 | L40: Lab | M40: Ele 2 | N40: =IF(K40="","","Active")
A41: 010I61 | B41: II | C41: ESE 5294 | D41: IT Project Management Lab | G41: * | I41: * | J41: 40 | L41: Lab | M41: Ele 2 | N41: =IF(K41="","","Active")
A42: 010I61 | B42: II | C42: MPT 5200 | D42: Mini Project - II | E42: * | F42: * | G42: * | H42: * | I42: * | J42: 41 | L42: Project | M42: Core | N42: =IF(K42="","","Active")
A43: 010I61 | B43: II | C43: PSD 5200 | D43: Professional Skill Development - II | G43: * | H43: * | I43: * | J43: 42 | L43: Seminar | M43: Core | N43: =IF(K43="","","Active")
A44: 010I62 | B44: I | C44: ESE 5101 | D44: Advanced Computer Architecture | G44: * | H44: * | I44: * | J44: 43 | K44: ACA | L44: Theory | M44: Core | N44: =IF(K44="","","Active") -> Active
A45: 010I62 | B45: I | C45: ESE 5102 | D45: Data Structures and Algorithms | G45: * | H45: * | I45: * | J45: 44 | K45: DSA | L45: Theory | M45: Core | N45: =IF(K45="","","Active") -> Active
A46: 010I62 | B46: I | C46: ESE 5103 | D46: Microcontrollers and its Applications | G46: * | H46: * | I46: * | J46: 45 | K46: MCA | L46: Theory | M46: Core | N46: =IF(K46="","","Active") -> Active
A47: 010I62 | B47: I | C47: ESE 5104 | D47: Real Time Operating Systems | G47: * | H47: * | I47: * | J47: 46 | K47: RTOS | L47: Theory | M47: Core | N47: =IF(K47="","","Active") -> Active
A48: 010I62 | B48: I | C48: ESE 5105 | D48: Embedded Systems | G48: * | H48: * | I48: * | J48: 47 | K48: ES | L48: Theory | M48: Core | N48: =IF(K48="","","Active") -> Active
A49: 010I62 | B49: I | C49: ESE 5151 | D49: Advanced Computer Architecture Lab | G49: * | H49: * | I49: * | J49: 48 | K49: ACA Lab | L49: Lab | M49: Core | N49: =IF(K49="","","Active") -> Active
A50: 010I62 | B50: I | C50: ESE 5152 | D50: Data Structures and Algorithms Lab | G50: * | H50: * | I50: * | J50: 49 | K50: DSA Lab | L50: Lab | M50: Core | N50: =IF(K50="","","Active") -> Active
A51: 010I62 | B51: I | C51: ESE 5153 | D51: Microcontrollers and its Applications Lab | G51: * | H51: * | J51: 50 | K51: MCA Lab | L51: Lab | M51: Core | N51: =IF(K51="","","Active") -> Active
A52: 010I62 | B52: I | C52: ESE 5154 | D52: Real Time Operating Systems Lab | G52: * | H52: * | I52: * | J52: 51 | K52: RTOS Lab | L52: Lab | M52: Core | N52: =IF(K52="","","Active") -> Active
A53: 010I62 | B53: I | C53: ESE 5155 | D53: Embedded Systems Lab | G53: * | H53: * | J53: 52 | K53: ES Lab | L53: Lab | M53: Core | N53: =IF(K53="","","Active") -> Active
A54: 010I62 | B54: I | C54: MPT 5100 | D54: Mini Project - I | E54: * | F54: * | G54: * | H54: * | I54: * | J54: 53 | K54: MP 1 | L54: Project | M54: Core | N54: =IF(K54="","","Active") -> Active
A55: 010I62 | B55: I | C55: PSD 5100 | D55: Professional Skill Development - I | E55: * | F55: * | J55: 54 | K55: PSD 1 | L55: Seminar | M55: Core | N55: =IF(K55="","","Active") -> Active
A56: 010I62 | B56: II | C56: ESE 5201 | D56: Device Drivers | G56: * | I56: * | J56: 55 | L56: Theory | M56: Core | N56: =IF(K56="","","Active")
A57: 010I62 | B57: II | C57: ESE 5202 | D57: Embedded Software Design | G57: * | H57: * | I57: * | J57: 56 | L57: Theory | M57: Core | N57: =IF(K57="","","Active")
A58: 010I62 | B58: II | C58: ESE 5203 | D58: Multicore Program Optimization | G58: * | H58: * | I58: * | J58: 57 | L58: Theory | M58: Core | N58: =IF(K58="","","Active")
A59: 010I62 | B59: II | C59: ESE 5231 | D59: Mobile Application Development using Android | G59: * | H59: * | I59: * | J59: 58 | L59: Theory | M59: Ele 1 | N59: =IF(K59="","","Active")
A60: 010I62 | B60: II | C60: ESE 5232 | D60: Web Application Development | G60: * | J60: 59 | L60: Theory | M60: Ele 1 | N60: =IF(K60="","","Active")
A61: 010I62 | B61: II | C61: ESE 5233 | D61: Machine Learning for Embedded Systems | G61: * | H61: * | I61: * | J61: 60 | L61: Theory | M61: Ele 1 | N61: =IF(K61="","","Active")
A62: 010I62 | B62: II | C62: ESE 5234 | D62: Entrepreneurship | G62: * | H62: * | J62: 61 | L62: Theory | M62: Ele 1 | N62: =IF(K62="","","Active")
A63: 010I62 | B63: II | C63: VDE 5232 | D63: System on Chip Design | G63: * | H63: * | J63: 62 | L63: Theory | M63: Ele 1 | N63: =IF(K63="","","Active")
A64: 010I62 | B64: II | C64: BDE 5002 | D64: Principles of Data Visualization | G64: * | I64: * | J64: 63 | L64: Theory | M64: Ele 1 | N64: =IF(K64="","","Active")
A65: 010I62 | B65: II | C65: ESE 5241 | D65: Computer Networks | G65: * | H65: * | J65: 64 | L65: Theory | M65: Ele 2 | N65: =IF(K65="","","Active")
A66: 010I62 | B66: II | C66: ESE 5242 | D66: Internet of Things | G66: * | I66: * | J66: 65 | L66: Theory | M66: Ele 2 | N66: =IF(K66="","","Active")
A67: 010I62 | B67: II | C67: ESE 5243 | D67: Database Programming in Java | G67: * | H67: * | I67: * | J67: 66 | L67: Theory | M67: Ele 2 | N67: =IF(K67="","","Active")
A68: 010I62 | B68: II | C68: ESE 5244 | D68: IT Project Management | G68: * | H68: * | J68: 67 | L68: Theory | M68: Ele 2 | N68: =IF(K68="","","Active")
A69: 010I62 | B69: II | C69: ESE 5245 | D69: Virtual Prototyping | G69: * | H69: * | I69: * | J69: 68 | L69: Theory | M69: Ele 2 | N69: =IF(K69="","","Active")
A70: 010I62 | B70: II | C70: ESE 5251 | D70: Device Drivers Lab | G70: * | I70: * | J70: 69 | L70: Lab | M70: Core | N70: =IF(K70="","","Active")
A71: 010I62 | B71: II | C71: ESE 5252 | D71: Embedded Software Design Lab | G71: * | H71: * | J71: 70 | L71: Lab | M71: Core | N71: =IF(K71="","","Active")
A72: 010I62 | B72: II | C72: ESE 5253 | D72: Multicore Program Optimization Lab | G72: * | H72: * | I72: * | J72: 71 | L72: Lab | M72: Core | N72: =IF(K72="","","Active")
A73: 010I62 | B73: II | C73: ESE 5281 | D73: Mobile Application Development using Android Lab | G73: * | H73: * | I73: * | J73: 72 | L73: Lab | M73: Ele 1 | N73: =IF(K73="","","Active")
A74: 010I62 | B74: II | C74: ESE 5282 | D74: Web Application Development Lab | G74: * | J74: 73 | L74: Lab | M74: Ele 1 | N74: =IF(K74="","","Active")
A75: 010I62 | B75: II | C75: ESE 5283 | D75: Machine Learning for Embedded Systems Lab | G75: * | H75: * | I75: * | J75: 74 | L75: Lab | M75: Ele 1 | N75: =IF(K75="","","Active")
A76: 010I62 | B76: II | C76: ESE 5284 | D76: Entrepreneurship Lab | G76: * | H76: * | J76: 75 | L76: Lab | M76: Ele 1 | N76: =IF(K76="","","Active")
A77: 010I62 | B77: II | C77: VDE 5282 | D77: System on Chip Design Lab | G77: * | H77: * | I77: * | J77: 76 | L77: Lab | M77: Ele 1 | N77: =IF(K77="","","Active")
A78: 010I62 | B78: II | C78: BDE 5052 | D78: Principles of Data Visualization Lab | G78: * | I78: * | J78: 77 | L78: Lab | M78: Ele 1 | N78: =IF(K78="","","Active")
A79: 010I62 | B79: II | C79: ESE 5291 | D79: Computer Networks Lab | G79: * | H79: * | J79: 78 | L79: Lab | M79: Ele 2 | N79: =IF(K79="","","Active")
A80: 010I62 | B80: II | C80: ESE 5292 | D80: Internet of Things Lab | G80: * | I80: * | J80: 79 | L80: Lab | M80: Ele 2 | N80: =IF(K80="","","Active")
A81: 010I62 | B81: II | C81: ESE 5293 | D81: Database Programming in Java Lab | G81: * | H81: * | I81: * | J81: 80 | L81: Lab | M81: Ele 2 | N81: =IF(K81="","","Active")
A82: 010I62 | B82: II | C82: ESE 5294 | D82: IT Project Management Lab | G82: * | I82: * | J82: 81 | L82: Lab | M82: Ele 2 | N82: =IF(K82="","","Active")
A83: 010I62 | B83: II | C83: ESE 5295 | D83: Virtual Prototyping Lab | G83: * | H83: * | I83: * | J83: 82 | L83: Lab | M83: Ele 2 | N83: =IF(K83="","","Active")
A84: 010I62 | B84: II | C84: MPT 5200 | D84: Mini Project - II | E84: * | F84: * | G84: * | H84: * | I84: * | J84: 83 | L84: Project | M84: Core | N84: =IF(K84="","","Active")
A85: 010I62 | B85: II | C85: PSD 5200 | D85: Professional Skill Development - II | G85: * | H85: * | I85: * | J85: 84 | L85: Seminar | M85: Core | N85: =IF(K85="","","Active")
A86: 010I63 | B86: I | C86: MVE 5001 | D86: IC Packaging Technology | G86: * | H86: * | J86: 85 | K86: ICPT | L86: Theory | M86: Core | N86: =IF(K86="","","Active") -> Active
A87: 010I63 | B87: I | C87: MVE 5101 | D87: VLSI Fabrication Technology | G87: * | H87: * | J87: 86 | K87: VFT | L87: Theory | M87: Core | N87: =IF(K87="","","Active") -> Active
A88: 010I63 | B88: I | C88: VDE 5102 | D88: Digital Systems and VLSI Design | G88: * | H88: * | I88: * | J88: 87 | K88: DSVD | L88: Theory | M88: Core | N88: =IF(K88="","","Active") -> Active
A89: 010I63 | B89: I | C89: VDE 5103 | D89: High Level Digital Design | G89: * | H89: * | J89: 88 | K89: HLDD | L89: Theory | M89: Core | N89: =IF(K89="","","Active") -> Active
A90: 010I63 | B90: I | C90: VDE 5104 | D90: Verification | G90: * | H90: * | J90: 89 | K90: VER | L90: Theory | M90: Core | N90: =IF(K90="","","Active") -> Active
A91: 010I63 | B91: I | C91: MVE 5051 | D91: IC Packaging Technology Lab | G91: * | H91: * | I91: * | J91: 90 | K91: ICPT Lab | L91: Lab | M91: Core | N91: =IF(K91="","","Active") -> Active
A92: 010I63 | B92: I | C92: MVE 5151 | D92: VLSI Fabrication Technology Lab | G92: * | H92: * | I92: * | J92: 91 | K92: VFT Lab | L92: Lab | M92: Core | N92: =IF(K92="","","Active") -> Active
A93: 010I63 | B93: I | C93: VDE 5152 | D93: Digital Systems and VLSI Design Lab | G93: * | H93: * | I93: * | J93: 92 | K93: DSVD Lab | L93: Lab | M93: Core | N93: =IF(K93="","","Active") -> Active
A94: 010I63 | B94: I | C94: VDE 5153 | D94: High Level Digital Design Lab | G94: * | H94: * | I94: * | J94: 93 | K94: HLDD Lab | L94: Lab | M94: Core | N94: =IF(K94="","","Active") -> Active
A95: 010I63 | B95: I | C95: VDE 5154 | D95: Verification Lab | G95: * | H95: * | I95: * | J95: 94 | K95: VER Lab | L95: Lab | M95: Core | N95: =IF(K95="","","Active") -> Active
A96: 010I63 | B96: I | C96: MPT 5100 | D96: Mini Project - I | E96: * | F96: * | G96: * | H96: * | I96: * | J96: 95 | K96: MP 1 | L96: Project | M96: Core | N96: =IF(K96="","","Active") -> Active
A97: 010I63 | B97: I | C97: PSD 5100 | D97: Professional Skill Development - I | E97: * | F97: * | J97: 96 | K97: PSD 1 | L97: Seminar | M97: Core | N97: =IF(K97="","","Active") -> Active
A98: 010I63 | B98: II | C98: MVE 5201 | D98: Process and Device Characterization | G98: * | H98: * | J98: 97 | L98: Theory | M98: Core | N98: =IF(K98="","","Active")
A99: 010I63 | B99: II | C99: VDE 5201 | D99: Advanced VLSI Design | G99: * | H99: * | I99: * | J99: 98 | L99: Theory | M99: Core | N99: =IF(K99="","","Active")
A100: 010I63 | B100: II | C100: VDE 5202 | D100: Physical Design | G100: * | H100: * | J100: 99 | L100: Theory | M100: Core | N100: =IF(K100="","","Active")
...

Sheet PEOs
A1: PEO Master | E1: Selected PEO
A2: Program | B2: PEO | C2: Description | E2: PEO | F2: Description
A3: 010I38 | B3: PEO 1 | C3: Successfully engage in challenging careers with professional approach in the areas of analog and digital VLSI design and related domains of engineering. | E3: {=_xlfn._xlws.FILTER($B$3:$C$100,$A$3:$A$100=Setup!$B$7,"")} -> PEO 1 | F3: Enable to draw upon fundamental and advanced knowledge to apply analytical and computational approaches to solve technological problems in computer science.
A4: 010I38 | B4: PEO 2 | C4: Demonstrate competence in identifying and analysing technical problems, suggest feasible and innovative solutions using their core competence in VLSI design and thereby support the technological growth of the nation. | E4: PEO 2 | F4: Introduce state of art technologies in computer science and inculcate ethical practices to make industry-ready professionals.
A5: 010I38 | B5: PEO 3 | C5: Impart quality technical education, engage in research and contribute to knowledge creation and sharing. | E5: PEO 3 | F5: Promote scientific and societal advancement through research and entrepreneurship.
A6: 010I38 | B6: PEO 4 | C6: Possess analytical, communicative and leadership skills, and demonstrate the ability to work in multidisciplinary and multi-cultural environments.
A7: 010I38 | B7: PEO 5 | C7: Be self-motivated and remain continuously employable by engaging in lifelong learning.
A8: 010I39 | B8: PEO 1 | C8: Enable to draw upon fundamental and advanced knowledge to apply analytical and computational approaches to solve technological problems in embedded systems.
A9: 010I39 | B9: PEO 2 | C9: Introduce state of art technologies in the area of embedded systems and inculcate ethical practices to make industry-ready professionals.
A10: 010I39 | B10: PEO 3 | C10: Promote scientific and societal advancement through research and entrepreneurship.
A11: 010I47 | B11: PEO 1 | C11: Develop advanced knowledge and understanding of the theories, concepts, and principles related to Cloud Computing, including virtualization, distributed systems, cloud networks, security, microservices, and cloud infrastructure management services.
A12: 010I47 | B12: PEO 2 | C12: Apply critical thinking and problem-solving skills to address complex challenges in cloud computing such as scalability, resource scheduling, performance optimization and data management.
A13: 010I47 | B13: PEO 3 | C13: Gain practical, hands-on experience with global cloud provider services, DevOps tools, automation and container orchestration services through coursework and applied research experiences.
A14: 010I57 | B14: PEO 1 | C14: Acquire solid mathematical and computational skills essential for understanding, applying, and developing modern artificial intelligence and machine learning algorithms.
A15: 010I57 | B15: PEO 2 | C15: Produce industry-ready graduates with practical experience in structuring machine learning projects using state-of-the-art software.
A16: 010I57 | B16: PEO 3 | C16: Address multi-disciplinary challenges through coursework and projects by adapting to the rapidly advancing developments in artificial intelligence and machine learning approaches.
A17: 010I58 | B17: PEO 1 | C17: Develop in depth understanding of the key technologies in data engineering, data science and business analytics.
... A62: 010I69 | B62: PEO 5 | C62: Be self-motivated and remain continuously employable by engaging in lifelong learning.

Sheet POs
A1: PO Master | E1: POs for Mappting | I1: Selected PO
A2: Program | B2: PO | C2: Description | E2: PO Details | I2: PO | J2: Description
A3: 010I38 | B3: PO 1 | C3: An ability to independently carry out research /investigation and development work to solve practical problems. | E3: Pos | F3: Available | G3: Filter | I3: {=_xlfn._xlws.FILTER($B$3:$C$100,$A$3:$A$100=Setup!$B$7,"")} -> PO 1 | J3: An ability to independently carry out research /investigation and development work to solve practical problems.
A4: 010I38 | B4: PO 2 | C4: An ability to write and present a substantial technical report/document. | E4: PO1 | F4: {=TRANSPOSE(_xlfn._xlws.FILTER(Course!$E$2:$I$600,(Course!$A$2:$A$600=Setup!B7)*(Course!$C$2:$C$600=Setup!B8)*(Course!$B$2:$B$600=Setup!#REF!)*(Course!#REF!=Setup!B3),""))} -> #REF! | G4: {=_xlfn._xlws.FILTER($E$4:$E$8,$F$4:$F$8="*","")} -> #REF! | I4: PO 2 | J4: An ability to write and present a substantial technical report/document.
A5: 010I38 | B5: PO 3 | C5: An ability to demonstrate a degree of mastery over the area as per the specialization of the program. The mastery should be at a level higher than the requirements in the appropriate bachelor's program. | E5: PO2 | I5: PO 3 | J5: An ability to demonstrate a degree of mastery over the area as per the specialization of the program. The mastery should be at a level higher than the requirements in the appropriate bachelor program.
A6: 010I38 | B6: PO 4 | C6: An ability to demonstrate knowledge of underlying principles and evaluation methods for integrated circuit technology. | E6: PO3 | I6: PO 4 | J6: An ability to develop software based on theoretical principles and practical knowledge.
A7: 010I38 | B7: PO 5 | C7: An ability to use modern tools for engineering design problems, analyze the performance and optimize the systems-level approaches. | E7: PO4 | I7: PO 5 | J7: An ability to demonstrate knowledge of the underlying principles and evaluation methods for analysing and decision-making.
A8: 010I39 | B8: PO 1 | C8: An ability to independently carry out research /investigation and development work to solve practical problems. | E8: PO5
A9: 010I39 | B9: PO 2 | C9: An ability to write and present a substantial technical report/document.
A10: 010I39 | B10: PO 3 | C10: An ability to demonstrate a degree of mastery over the area as per the specialization of the program. The mastery should be at a level higher than the requirements in the appropriate bachelor program.
A11: 010I39 | B11: PO 4 | C11: An ability to develop and implement embedded systems requirements based on theoretical principles and practical knowledge.
A12: 010I39 | B12: PO 5 | C12: An ability to demonstrate knowledge of the underlying principles and evaluation methods for analyzing and decision-making.
A13: 010I47 | B13: PO 1 | C13: An ability to independently carry out research /investigation and development work to solve practical problems.
A14: 010I47 | B14: PO 2 | C14: An ability to write and present a substantial technical report/document.
A15: 010I47 | B15: PO 3 | C15: An ability to demonstrate a degree of mastery over the area as per the specialization of the program. The mastery should be at a level higher than the requirements in the appropriate bachelor program.
A16: 010I47 | B16: PO 4 | C16: An ability to design, develop scalable, highly available and fault-tolerant cloud solutions, services for business needs and implement well architected cloud architectures based on theoretical principles, ethical considerations, and detailed knowledge of the underlying infrastructure, applications and data.
A17: 010I47 | B17: PO 5 | C17: An ability to demonstrate knowledge of securing cloud resources, data and infrastructure and apply DevOps best practices to automate software development life cycle.
A18: 010I57 | B18: PO 1 | C18: An ability to independently carry out research/investigation and development work to solve practical problems.
A19: 010I57 | B19: PO 2 | C19: An ability to write and present a substantial technical report/document.
A20: 010I57 | B20: PO 3 | C20: Demonstrate a degree of mastery over the area as per the specialization of the program which should be at a level higher than the requirements in an appropriate bachelor program.
... A82: 010I69 | B82: PO 5 | C82: Develop knowledge in Cybersecurity to monitor, prevent, predict and detect and countermeasure cyberattacks using tools and techniques using appropriate security tools.

Sheet COs
A1: Program | B1: Semester | C1: Subject Code | D1: Subject Name | E1: COs | F1: Course Outcome | G1: No. of Hours
A2: 010I61 | B2: I | C2: AME 5002 | D2: Applied Machine Learning | E2: CO1 | F2: Apply different types of supervised machine learning algorithms to practical problems. | G2: 12
A3: 010I61 | B3: I | C3: AME 5002 | D3: Applied Machine Learning | E3: CO2 | F3: Apply different types of unsupervised machine learning algorithms to practical problems. | G3: 12
A4: 010I61 | B4: I | C4: AME 5002 | D4: Applied Machine Learning | E4: CO3 | F4: Analyse different types of machine learning paradigms. | G4: 12
A5: 010I61 | B5: I | C5: AME 5101 | D5: Applied Linear Algebra | E5: CO1 | F5: Apply vector operations for similarity learning. | G5: 10
A6: 010I61 | B6: I | C6: AME 5101 | D6: Applied Linear Algebra | E6: CO2 | F6: Analyse matrix representations in AI & ML models. | G6: 14
A7: 010I61 | B7: I | C7: AME 5101 | D7: Applied Linear Algebra | E7: CO3 | F7: Apply matrix calculus for optimization in learning systems. | G7: 12
A8: 010I61 | B8: I | C8: CCE 5101 | D8: Cloud Application with JAVA and Database with Java | E8: CO1 | F8: Apply Java programming techniques and data interface concepts for application development. | G8: 16
A9: 010I61 | B9: I | C9: CCE 5101 | D9: Cloud Application with JAVA and Database with Java | E9: CO2 | F9: Analyse the techniques to be used for high availability and fault tolerant cloud applications. | G9: 14
A10: 010I61 | B10: I | C10: CCE 5101 | D10: Cloud Application with JAVA and Database with Java | E10: CO3 | F10: Understand the Cloud application architecture and design principles. | G10: 6
A11: 010I61 | B11: I | C11: ESE 5102 | D11: Data Structures and Algorithms | E11: CO1 | F11: Analyse the implementations of elementary data structures. | G11: 12
A12: 010I61 | B12: I | C12: ESE 5102 | D12: Data Structures and Algorithms | E12: CO2 | F12: Design and implementation of data structures like trees and graphs. | G12: 15
A13: 010I61 | B13: I | C13: ESE 5102 | D13: Data Structures and Algorithms | E13: CO3 | F13: Analyse the concepts of divide and conquer, dynamic programming, greedy, and back tracking techniques to efficiently solve problems. | G13: 9
... A504: 010I65 | B504: I | C504: ESE 5105 | D504: Embedded Systems | E504: CO3 | F504: Design multi-tasking applications using real-time operating systems. | G504: 12
A505: 010I65 | B505: I | C505: ESE 5108 | D505: French Language-1* | E505: CO1
A506: 010I65 | B506: I | C506: ESE 5108 | D506: French Language-1* | E506: CO2
A507: 010I65 | B507: I | C507: ESE 5108 | D507: French Language-1* | E507: CO3
A508: 010I65 | B508: I | C508: ESE 5156 | D508: Sensors and Transducers Lab | E508: CO1 | F508: Apply the knowledge of resistive sensors, strain gauge, inductive, and capacitive sensors to develop applications. | G508: 12
A509: 010I65 | B509: I | C509: ESE 5156 | D509: Sensors and Transducers Lab | E509: CO2 | F509: Apply the principles behind ultrasonic and thermal sensors to develop applications. | G509: 12
A510: 010I65 | B510: I | C510: ESE 5156 | D510: Sensors and Transducers Lab | E510: CO3 | F510: Design automation through sensor feedback. | G510: 12
A511: 010I65 | B511: I | C511: ESE 5157 | D511: Vehicular Adhoc Networks Lab | E511: CO1 | F511: Understand the simulation tools for VANET. | G511: 15
A512: 010I65 | B512: I | C512: ESE 5157 | D512: Vehicular Adhoc Networks Lab | E512: CO2 | F512: Apply VANET simulation for routing and traffic applications. | G512: 12
A513: 010I65 | B513: I | C513: ESE 5157 | D513: Vehicular Adhoc Networks Lab | E513: CO3 | F513: Apply emerging technologies to solve real-world challenges in VANETs. | G513: 9
A514: 010I65 | B514: I | C514: ESE 5153 | D514: Microcontrollers and its Applications Lab | E514: CO1 | F514: Apply the knowledge of Microcontrollers to build embedded systems. | G514: 15
A515: 010I65 | B515: I | C515: ESE 5153 | D515: Microcontrollers and its Applications Lab | E515: CO2 | F515: Apply the concepts of timers, and counters for interfacing. | G515: 9
A516: 010I65 | B516: I | C516: ESE 5153 | D516: Microcontrollers and its Applications Lab | E516: CO3 | F516: Analyse the features of SPI, I2C, and interface components to microcontrollers. | G516: 12
A517: 010I65 | B517: I | C517: ESE 5154 | D517: Real Time Operating Systems Lab | E517: CO1 | F517: Implement C programs to efficiently solve problems using multiple processes. | G517: 15
A518: 010I65 | B518: I | C518: ESE 5154 | D518: Real Time Operating Systems Lab | E518: CO2 | F518: Execute C programs for process scheduling and deadlock avoidance algorithms. | G518: 6
A519: 010I65 | B519: I | C519: ESE 5154 | D519: Real Time Operating Systems Lab | E519: CO3 | F519: Design multithreaded programs to solve problems considering process scheduling, deadlocks, or process synchronization on a given scenario. | G519: 15
... A976: 010I69 | B976: II | C976: PSD 5200 | D976: Professional Skill Development - II | E976: CO3 | F976: Use mathematical, reasoning, and domain specific skills to solve objective questionnaires in time. | G976: 4

Sheet References
A1: Program | B1: Semester | C1: Subject Code | D1: Subject Name | E1: References
A2: 010I61 | B2: I | C2: AME 5002 | D2: Applied Machine Learning | E2: 1. G. James, D. Witten, T. Hastie, R. Tibshirani, and J. Taylor, An Introduction to Statistical Learning: with Applications in Python, Springer Texts in Statistics. Cham, Switzerland: Springer, 2023. Online resource available at https://www.statlearning.com/ 2. L. G. Serrano, Grokking Machine Learning, S. Thrun, Foreword, Manning Publications, 2021. Online resource from Manning Publications available at https://www.manning.com/books/grokking-machine-learning 3. J. VanderPlas, Python Data Science Handbook, Sebastopol, CA: O’Reilly Media, 2016. 4. A Course in Machine Learning, Hal Daumé III – Online resource available at http://ciml.info/ 5. Module: Introduction to Machine Learning (https://www.intel.com/content/www/us/en/developer/tools/oneapi/training/academic-program/educators/intro-machine-learning-training-kit.html). 6. Learning path: Understand data science for machine learning (https://learn.microsoft.com/en-us/training/paths/understand-machine-learning/).
A3: 010I61 | B3: I | C3: AME 5101 | D3: Applied Linear Algebra | E3: 1. Introduction to Applied Linear Algebra, Vectors, Matrices, and Least Squares, Stephen Boyd & Lieven Vandenberghe, Cambridge University Press, 1st Edition, 2018. Available online at http://vmls-book.stanford.edu/vmls.pdf. 2. Linear Algebra and Learning from Data, Gilbert Strang, Cambridge Uni. Press, 1st Edition, 2019. 3. IBM AI Engineering Professional Certificate (https://www.coursera.org/professional- certificates/ai-engineer). 4. Deep Learning with Python, François Chollet, Manning Publications, 2nd Edition, 2021. 5. Neural Networks and Deep Learning, Michael A. Nielsen, Determination Press, 2015. Available online at http://neuralnetworksanddeeplearning.com/ 6. Matrix Methods: Applied Linear Algebra, Richard Bronson and Gabriel B. Costa, Academic Press, 3rd Edition, 2008. 7. Introduction to computational thinking (https://computationalthinking.mit.edu/Fall24/).
A4: 010I61 | B4: I | C4: CCE 5101 | D4: Cloud Application with JAVA and Database with Java | E4: 1. Archdeep Bahaga, Vijay Madisetti, “Cloud Computing-A hands on Approach”, Universities Press, 2014. 2. Patrick Naughton and Herbert Schildt, "JAVA 2 – The Complete Reference7th & 8th Edition, Tata McGraw Hill, 2012. 3. Paul Deitel, Harvey Deitel , “How to program with JAVA”, 9th Edition , Deitel Publications, 2012. 4. Abraham Silberschatz, Henry F. Korth and S. Sudharshan, Database System Concepts, Sixth Edition, Tata Mc Graw Hill, 2011. 5. C.J.Date, A.Kannan and S.Swamynathan, An Introduction to Database Systems, Eighth, Edition, Pearson Education, 2006. 6. Atul Kahate, Introduction to Database Management Systems, Pearson Education, New Delhi, 2006. 7. Alexis Leon and Mathews Leon, Database Management Systems, Vikas Publishing House Private Limited, New Delhi, 2003. 8. Raghu Ramakrishnan, Database Management Systems, Fourth Edition, Tata Mc Graw Hill, 2010. 9. Articles, White papers and Transaction Papers. 9. https://www.coursera.org/learn/database-design-postgresql
A5: 010I61 | B5: I | C5: ESE 5102 | D5: Data Structures and Algorithms | E5: 1. “Introduction to Algorithms” Thomas H. Cormen, Charles E. Leiserson, Ronald L. Rivest. 2. “Data Structures& Algorithms” Aho, Hopcroft and Ulmann. 3. “Data structures and algorithm analysis in C” Mark Allen Weiss. 4. “Computer Algorithms” : Ellis Horowitz, Sartaj Sahni, Sanguthevar Rajasekaran. 5. MOOC: https://in.coursera.org/learn/algorithms-on-graphs?specialization=data-structures- 6. algorithms#enroll
A6: 010I61 | B6: I | C6: ESE 5104 | D6: Real Time Operating Systems | E6: 1. “Operating System principles”, Seventh Edition, Abraham Silberschatz, Peter Galvvin, Grag Gagne. John Wiley Publications. 2. “Real – Time Systems and Programming Languages”, Allan Burns, Andy Wellings. 3. “Operating Stems Concepts and Design”, Milan Milenkovic. 4. “Design of Unix Operating System”, Maurice Bach (IPC) 5. “The C Programming Language”, Kerninghan & Ritchie. 6. MOOC:https://in.coursera.org/learn/real-time-embedded-systems-concepts-practices#syllabus.
A7: 010I61 | B7: I | C7: AME 5052 | D7: Applied Machine Learning Lab | E7: 1. G. James, D. Witten, T. Hastie, R. Tibshirani, and J. Taylor, An Introduction to Statistical Learning: with Applications in Python, Springer Texts in Statistics. Cham, Switzerland: Springer, 2023. Online resource available at https://www.statlearning.com/ 2. L. G. Serrano, Grokking Machine Learning, S. Thrun, Foreword, Manning Publications, 2021. Online resource from Manning Publications available at https://www.manning.com/books/grokking-machine-learning 3. J. VanderPlas, Python Data Science Handbook, Sebastopol, CA: O’Reilly Media, 2016. 4. A Course in Machine Learning, Hal Daumé III – Online resource available at http://ciml.info/ 5. Module: Introduction to Machine Learning (https://www.intel.com/content/www/us/en/developer/tools/oneapi/training/academic-program/educators/intro-machine-learning-training-kit.html). 6. Learning path: Understand data science for machine learning (https://learn.microsoft.com/en-us/training/paths/understand-machine-learning/).
A8: 010I61 | B8: I | C8: AME 5151 | D8: Applied Linear Algebra Lab | E8: 1. S. Boyd and L. Vandenberghe, *Introduction to Applied Linear Algebra: Vectors, Matrices, and Least Squares*, 1st ed. Cambridge, U.K.: Cambridge University Press, 2018. [Online]. Available: http://vmls-book.stanford.edu/vmls.pdf 2. G. Strang, *Linear Algebra and Learning from Data*, 1st ed. Cambridge, U.K.: Cambridge University Press, 2019. 3. IBM, “AI Engineering Professional Certificate,” Coursera. [Online]. Available: https://www.coursera.org/professional-certificates/ai-engineer 4. F. Chollet, *Deep Learning with Python*, 2nd ed. Shelter Island, NY, USA: Manning Publications, 2021. 5. M. A. Nielsen, *Neural Networks and Deep Learning*. Determination Press, 2015. [Online]. Available: http://neuralnetworksanddeeplearning.com/ 6. R. Bronson and G. B. Costa, *Matrix Methods: Applied Linear Algebra*, 3rd ed. Burlington, MA, USA: Academic Press, 2008. 7. Massachusetts Institute of Technology, “Introduction to Computational Thinking,” 2024. [Online]. Available: https://computationalthinking.mit.edu/Fall24/
A9: 010I61 | B9: I | C9: CCE 5151 | D9: Cloud Application with JAVA and Database with Java Lab | E9: 1. Archdeep Bahaga, Vijay Madisetti, “Cloud Computing-A hands on Approach”, Universities Press, 2014. 2. Archdeep Bahaga, Vijay Madisetti, “Internet of Things - A hands on Approach”, Universities Press, 2015. 3. Patrick Naughton and Herbert Schildt, "JAVA 2 – The Complete Reference7th & 8th Edition, Tata McGraw Hill, 2012. 4. Paul Deitel, Harvey Deitel, “How to program with JAVA”, 9th Edition, Deitel Publications, 2012. 5. Danny Coward, “Java WebSocket Programming”, McGraw-Hill Education, 2014. 6. Jobinesh Purushothaman,” RESTful Java Web Services”, Second Edition, Packt Publishing, 2015.
A10: 010I61 | B10: I | C10: ESE 5152 | D10: Data Structures and Algorithms Lab | E10: 1. Introduction to Algorithms – Thomas H. Cormen, Charles E. Leiserson, Ronald L. Rivest. MIT Press. 2. Data Structures and Algorithms – Aho, Hopcroft and Ulmann. Pearson Publishers.
A11: 010I61 | B11: I | C11: ESE 5154 | D11: Real Time Operating Systems Lab | E11: 1. “Operating System principles”, Seventh Edition, Abraham Silberschatz, Peter Galvvin, Grag Gagne. John Wiley Publications. 2. “Real – Time Systems and Programming Languages”, Allan Burns, Andy Wellings. 3. “Operating Stems Concepts and Design”, Milan Milenkovic. 4. “Design of Unix Operating System”, Maurice Bach (IPC). 5. “The C Programming Language”, Kerninghan & Ritchie.
A12: 010I61 | B12: I | C12: MPT 5100 | D12: Mini Project - I | E12: 1. Research Methodology, Methods and Techniques, C. R. Kothari; New Age International Publishers; 2nd Revised Edition,2004 2. (https://www.jsscacs.edu.in/sites/default/files/Files/Statistics%20and%20Research%20by%20Kothari.pdf). 3. Project Management by Adrienne Watt - BCcampus Open Textbook project 4. (https://www.opentextbooks.org.hk/system/files/export/15/15694/pdf/Project_Management_15694.pdf). 5. Research articles and Online Resources.
... A325: 010I69 | B325: II | C325: PSD 5200 | D325: Professional Skill Development - II | E325: 1. R S Aggarwal. Quantitative Aptitude for Competitive Examinations. S Chand, 2017. 2. McDowell, Gayle Laakmann. Cracking the coding interview: 189 programming questions and solutions. CareerCup, LLC, 2015. 3. Domain specific tools and online resources.

Sheet Course 24 & 25
A1: Batch | B1: Academic Year | C1: Program Code | D1: Semester | E1: Course Code | F1: Course Name | G1: PO1 | H1: PO2 | I1: PO3 | J1: PO4 | K1: PO5 | L1: Sort No | M1: Short Code | N1: Subject Class | O1: Status | Q1: Subject Code | R1: Subject Name
A2: 2024 | B2: 2024-2025 | C2: 010I38 | D2: I | E2: VLS 5001 | F2: High Level Digital Design | I2: * | J2: * | L2: 1 | M2: HLDD | N2: Theory | O2: Active | Q2: {=_xlfn._xlws.FILTER($E$2:$F$600,(N2:N600="Theory")*(O2:O600="Active")*('Course 24 & 25'!$C$2:$C$600=Setup!$B$7)*('Course 24 & 25'!$D$2:$D$600=Setup!#REF!),"")} -> #REF!
A3: 2024 | B3: 2024-2025 | C3: 010I38 | D3: I | E3: VLS 5101 | F3: Data Structures | G3: * | I3: * | J3: * | L3: 2 | M3: DS | N3: Theory | O3: Active
A4: 2024 | B4: 2024-2025 | C4: 010I38 | D4: I | E4: VLS 5102 | F4: Digital Systems and VLSI Design | I4: * | J4: * | K4: * | L4: 3 | M4: DSVD | N4: Theory | O4: Active
A5: 2024 | B5: 2024-2025 | C5: 010I38 | D5: I | E5: VLS 5103 | F5: Verification | I5: * | J5: * | L5: 4 | M5: VER | N5: Theory | O5: Active
A6: 2024 | B6: 2024-2025 | C6: 010I38 | D6: I | E6: VLS 5131 | F6: CAD for VLSI | G6: * | I6: * | K6: * | L6: 5 | M6: CAD | N6: Theory | O6: Active
A7: 2024 | B7: 2024-2025 | C7: 010I38 | D7: I | E7: VLS 5132 | F7: System on chip Design | I7: * | J7: * | L7: 6 | M7: SoC | N7: Theory | O7: Active
A8: 2024 | B8: 2024-2025 | C8: 010I38 | D8: I | E8: ESD 5001 | F8: Digital Signal Processing | G8: * | I8: * | J8: * | L8: 7 | N8: Theory
A9: 2024 | B9: 2024-2025 | C9: 010I38 | D9: I | E9: MVT 5101 | F9: VLSI Fabrication Technology | I9: * | J9: * | L9: 8 | N9: Theory
A10: 2024 | B10: 2024-2025 | C10: 010I38 | D10: I | E10: VLS 5051 | F10: High Level Digital Design Lab | I10: * | J10: * | K10: * | L10: 9 | M10: HLDD Lab | N10: Lab | O10: Active
A11: 2024 | B11: 2024-2025 | C11: 010I38 | D11: I | E11: VLS 5151 | F11: Data Structures Lab | G11: * | I11: * | J11: * | L11: 10 | M11: DS Lab | N11: Lab | O11: Active
A12: 2024 | B12: 2024-2025 | C12: 010I38 | D12: I | E12: VLS 5152 | F12: Digital Systems and VLSI Design Lab | I12: * | J12: * | K12: * | L12: 11 | M12: DSVD Lab | N12: Lab | O12: Active
A13: 2024 | B13: 2024-2025 | C13: 010I38 | D13: I | E13: VLS 5153 | F13: Verification Lab | I13: * | J13: * | L13: 12 | M13: VER Lab | N13: Lab | O13: Active
A14: 2024 | B14: 2024-2025 | C14: 010I38 | D14: I | E14: VLS 5181 | F14: CAD for VLSI Lab | G14: * | I14: * | K14: * | L14: 13 | M14: CAD Lab | N14: Lab | O14: Active
A15: 2024 | B15: 2024-2025 | C15: 010I38 | D15: I | E15: VLS 5182 | F15: System on chip Design Lab | J15: * | K15: * | L15: 14 | M15: SoC Lab | N15: Lab | O15: Active
A16: 2024 | B16: 2024-2025 | C16: 010I38 | D16: I | E16: ESD 5051 | F16: Digital Signal Processing Lab | G16: * | I16: * | J16: * | L16: 15 | N16: Lab
A17: 2024 | B17: 2024-2025 | C17: 010I38 | D17: I | E17: MVT 5151 | F17: VLSI Fabrication Technology Lab | I17: * | J17: * | L17: 16 | N17: Lab
A18: 2024 | B18: 2024-2025 | C18: 010I38 | D18: I | E18: MPT 5100 | F18: Mini Project - I | G18: * | H18: * | I18: * | J18: * | K18: * | L18: 17 | M18: MP 1 | N18: Project | O18: Active
A19: 2024 | B19: 2024-2025 | C19: 010I38 | D19: I | E19: PSD 5100 | F19: Professional Skill Development - I | G19: * | H19: * | L19: 18 | M19: PSD 1 | N19: Seminar | O19: Active
A20: 2024 | B20: 2024-2025 | C20: 010I38 | D20: II | E20: VLS 5201 | F20: Advanced VLSI Design | G20: * | I20: * | J20: * | K20: * | L20: 19 | M20: AVD | N20: Theory | O20: Active
A21: 2024 | B21: 2024-2025 | C21: 010I38 | D21: II | E21: VLS 5202 | F21: Low Power VLSI Design | G21: * | I21: * | J21: * | K21: * | L21: 20 | M21: LPVD | N21: Theory | O21: Active
A22: 2024 | B22: 2024-2025 | C22: 010I38 | D22: II | E22: VLS 5203 | F22: Scripting for VLSI | G22: * | I22: * | J22: * | L22: 21 | M22: SCR | N22: Theory | O22: Active
A23: 2024 | B23: 2024-2025 | C23: 010I38 | D23: II | E23: VLS 5204 | F23: Universal Verification Methodology | I23: * | J23: * | L23: 22 | M23: UVM | N23: Theory | O23: Active
A24: 2024 | B24: 2024-2025 | C24: 010I38 | D24: II | E24: VLS 5231 | F24: Advanced Logic Synthesis | I24: * | J24: * | L24: 23 | N24: Theory
A25: 2024 | B25: 2024-2025 | C25: 010I38 | D25: II | E25: VLS 5233 | F25: Machine learning for VLSI Design | I25: * | J25: * | L25: 24 | N25: Theory
A26: 2024 | B26: 2024-2025 | C26: 010I38 | D26: II | E26: VLS 5234 | F26: Physical Design | I26: * | J26: * | L26: 25 | M26: PD | N26: Theory | O26: Active
A27: 2024 | B27: 2024-2025 | C27: 010I38 | D27: II | E27: ENP 5230 | F27: Entrepreneurship | I27: * | J27: * | L27: 26 | N27: Theory
A28: 2024 | B28: 2024-2025 | C28: 010I38 | D28: II | E28: ESD 5232 | F28: IT Project Management | G28: * | I28: * | K28: * | L28: 27 | N28: Theory
A29: 2024 | B29: 2024-2025 | C29: 010I38 | D29: II | E29: VLS 5251 | F29: Advanced VLSI Design Lab | G29: * | I29: * | J29: * | K29: * | L29: 28 | M29: AVD Lab | N29: Lab | O29: Active
A30: 2024 | B30: 2024-2025 | C30: 010I38 | D30: II | E30: VLS 5252 | F30: Low Power VLSI Design Lab | G30: * | I30: * | J30: * | K30: * | L30: 29 | M30: LPVD Lab | N30: Lab | O30: Active
A31: 2024 | B31: 2024-2025 | C31: 010I38 | D31: II | E31: VLS 5253 | F31: Scripting for VLSI Lab | G31: * | I31: * | J31: * | L31: 30 | M31: SCR Lab | N31: Lab | O31: Active
A32: 2024 | B32: 2024-2025 | C32: 010I38 | D32: II | E32: VLS 5254 | F32: Universal Verification Methodology Lab | J32: * | K32: * | L32: 31 | M32: UVM Lab | N32: Lab | O32: Active
A33: 2024 | B33: 2024-2025 | C33: 010I38 | D33: II | E33: VLS 5281 | F33: Advanced Logic Synthesis Lab | I33: * | J33: * | L33: 32 | N33: Lab
A34: 2024 | B34: 2024-2025 | C34: 010I38 | D34: II | E34: VLS 5283 | F34: Machine Learning for VLSI Design Lab | I34: * | J34: * | L34: 33 | N34: Lab
A35: 2024 | B35: 2024-2025 | C35: 010I38 | D35: II | E35: VLS 5284 | F35: Physical Design Lab | J35: * | K35: * | L35: 34 | M35: PD Lab | N35: Lab | O35: Active
A36: 2024 | B36: 2024-2025 | C36: 010I38 | D36: II | E36: ENP 5280 | F36: Entrepreneurship Lab | I36: * | J36: * | L36: 35 | N36: Lab
A37: 2024 | B37: 2024-2025 | C37: 010I38 | D37: II | E37: ESD 5282 | F37: IT Project Management Lab | G37: * | I37: * | K37: * | L37: 36 | N37: Lab
A38: 2024 | B38: 2024-2025 | C38: 010I38 | D38: II | E38: MPT 5200 | F38: Mini Project - II | G38: * | H38: * | I38: * | J38: * | K38: * | L38: 37 | M38: MP 2 | N38: Project | O38: Active
A39: 2024 | B39: 2024-2025 | C39: 010I38 | D39: II | E39: PSD 5200 | F39: Professional Skill Development - II | I39: * | J39: * | K39: * | L39: 38 | M39: PSD 2 | N39: Seminar | O39: Active
A40: 2024 | B40: 2024-2025 | C40: 010I38 | D40: III & IV | E40: VLS 6098 | F40: Project Work | G40: * | H40: * | I40: * | J40: * | K40: * | L40: 39 | N40: Project
A41: 2024 | B41: 2024-2025 | C41: 010I39 | D41: I | E41: ESD 5101 | F41: Advanced Computer Architecture | G41: * | I41: * | J41: * | K41: * | L41: 40 | M41: ACA | N41: Theory | O41: Active
A42: 2024 | B42: 2024-2025 | C42: 010I39 | D42: I | E42: ESD 5102 | F42: Data Structures and Algorithms | G42: * | I42: * | J42: * | K42: * | L42: 41 | M42: DSA | N42: Theory | O42: Active
A43: 2024 | B43: 2024-2025 | C43: 010I39 | D43: I | E43: ESD 5103 | F43: Microcontrollers and its Applications | G43: * | I43: * | J43: * | K43: * | L43: 42 | M43: MCA | N43: Theory | O43: Active
A44: 2024 | B44: 2024-2025 | C44: 010I39 | D44: I | E44: ESD 5104 | F44: Real Time Operating Systems | G44: * | I44: * | J44: * | K44: * | L44: 43 | M44: RTOS | N44: Theory | O44: Active
A45: 2024 | B45: 2024-2025 | C45: 010I39 | D45: I | E45: ESD 5131 | F45: Computer Networks | G45: * | I45: * | J45: * | L45: 44 | N45: Theory
A46: 2024 | B46: 2024-2025 | C46: 010I39 | D46: I | E46: ESD 5132 | F46: Internet of Things | G46: * | I46: * | K46: * | L46: 45 | M46: IoT | N46: Theory | O46: Active
A47: 2024 | B47: 2024-2025 | C47: 010I39 | D47: I | E47: ESD 5133 | F47: Database Programming in Java | G47: * | I47: * | J47: * | K47: * | L47: 46 | M47: DPJ | N47: Theory | O47: Active
A48: 2024 | B48: 2024-2025 | C48: 010I39 | D48: I | E48: VLS 5132 | F48: System on Chip Design | I48: * | J48: * | L48: 47 | M48: SoC | N48: Theory | O48: Active
A49: 2024 | B49: 2024-2025 | C49: 010I39 | D49: I | E49: ESD 5151 | F49: Advanced Computer Architecture Lab | G49: * | I49: * | J49: * | K49: * | L49: 48 | M49: ACA Lab | N49: Lab | O49: Active
A50: 2024 | B50: 2024-2025 | C50: 010I39 | D50: I | E50: ESD 5152 | F50: Data Structures and Algorithms Lab | G50: * | I50: * | J50: * | K50: * | L50: 49 | M50: DSA Lab | N50: Lab | O50: Active
A51: 2024 | B51: 2024-2025 | C51: 010I39 | D51: I | E51: ESD 5153 | F51: Microcontrollers and its Applications Lab | G51: * | I51: * | J51: * | L51: 50 | M51: MCA Lab | N51: Lab | O51: Active
A52: 2024 | B52: 2024-2025 | C52: 010I39 | D52: I | E52: ESD 5154 | F52: Real Time Operating Systems Lab | G52: * | I52: * | J52: * | K52: * | L52: 51 | M52: RTOS Lab | N52: Lab | O52: Active
A53: 2024 | B53: 2024-2025 | C53: 010I39 | D53: I | E53: ESD 5181 | F53: Computer Networks Lab | G53: * | I53: * | J53: * | L53: 52 | N53: Lab
A54: 2024 | B54: 2024-2025 | C54: 010I39 | D54: I | E54: ESD 5182 | F54: Internet of Things Lab | G54: * | I54: * | K54: * | L54: 53 | M54: IoT Lab | N54: Lab | O54: Active
A55: 2024 | B55: 2024-2025 | C55: 010I39 | D55: I | E55: ESD 5183 | F55: Database Programming in Java Lab | G55: * | I55: * | J55: * | K55: * | L55: 54 | M55: DPJ Lab | N55: Lab | O55: Active
A56: 2024 | B56: 2024-2025 | C56: 010I39 | D56: I | E56: VLS 5182 | F56: System on Chip Design Lab | J56: * | K56: * | L56: 55 | M56: SoC Lab | N56: Lab | O56: Active
A57: 2024 | B57: 2024-2025 | C57: 010I39 | D57: I | E57: MPT 5100 | F57: Mini Project - I | G57: * | H57: * | I57: * | J57: * | K57: * | L57: 56 | M57: MP 1 | N57: Project | O57: Active
A58: 2024 | B58: 2024-2025 | C58: 010I39 | D58: I | E58: PSD 5100 | F58: Professional Skill Development - I | G58: * | H58: * | L58: 57 | M58: PSD 1 | N58: Seminar | O58: Active
A59: 2024 | B59: 2024-2025 | C59: 010I39 | D59: II | E59: ESD 5201 | F59: Device Drivers | G59: * | I59: * | K59: * | L59: 58 | M59: DD | N59: Theory | O59: Active
A60: 2024 | B60: 2024-2025 | C60: 010I39 | D60: II | E60: ESD 5202 | F60: Embedded Systems | G60: * | I60: * | J60: * | K60: * | L60: 59 | M60: ES | N60: Theory | O60: Active
A61: 2024 | B61: 2024-2025 | C61: 010I39 | D61: II | E61: ESD 5203 | F61: Embedded Software Design | G61: * | I61: * | J61: * | K61: * | L61: 60 | M61: ESD | N61: Theory | O61: Active
A62: 2024 | B62: 2024-2025 | C62: 010I39 | D62: II | E62: ESD 5235 | F62: Multicore Program Optimization | G62: * | I62: * | J62: * | K62: * | L62: 61 | M62: MPO | N62: Theory | O62: Active
A63: 2024 | B63: 2024-2025 | C63: 010I39 | D63: II | E63: BDA 5132 | F63: Principles of Data Visualization | I63: * | K63: * | L63: 62 | N63: Theory
A64: 2024 | B64: 2024-2025 | C64: 010I39 | D64: II | E64: ESD 5232 | F64: IT Project Management | G64: * | I64: * | K64: * | L64: 63 | N64: Theory
A65: 2024 | B65: 2024-2025 | C65: 010I39 | D65: II | E65: ESD 5233 | F65: Mobile Application Development using Android | G65: * | I65: * | J65: * | K65: * | L65: 64 | N65: Theory
A66: 2024 | B66: 2024-2025 | C66: 010I39 | D66: II | E66: ESD 5001 | F66: Digital Signal Processing | G66: * | I66: * | J66: * | L66: 65 | N66: Theory
A67: 2024 | B67: 2024-2025 | C67: 010I39 | D67: II | E67: ESD 5237 | F67: Web Application Development | G67: * | I67: * | L67: 66 | N67: Theory
A68: 2024 | B68: 2024-2025 | C68: 010I39 | D68: II | E68: ESD 5238 | F68: Virtual Prototyping | G68: * | I68: * | J68: * | K68: * | L68: 67 | M68: VP | N68: Theory | O68: Active
A69: 2024 | B69: 2024-2025 | C69: 010I39 | D69: II | E69: ENP 5230 | F69: Entrepreneurship | I69: * | J69: * | L69: 68 | N69: Theory
A70: 2024 | B70: 2024-2025 | C70: 010I39 | D70: II | E70: VLS 5001 | F70: High Level Digital Design | I70: * | J70: * | K70: * | L70: 69 | N70: Theory
A71: 2024 | B71: 2024-2025 | C71: 010I39 | D71: II | E71: ESD 5251 | F71: Device Drivers Lab | G71: * | I71: * | K71: * | L71: 70 | M71: DD Lab | N71: Lab | O71: Active
A72: 2024 | B72: 2024-2025 | C72: 010I39 | D72: II | E72: ESD 5252 | F72: Embedded Systems Lab | G72: * | I72: * | J72: * | L72: 71 | M72: ES Lab | N72: Lab | O72: Active
A73: 2024 | B73: 2024-2025 | C73: 010I39 | D73: II | E73: ESD 5253 | F73: Embedded Software Design Lab | G73: * | I73: * | J73: * | L73: 72 | M73: ESD Lab | N73: Lab | O73: Active
A74: 2024 | B74: 2024-2025 | C74: 010I39 | D74: II | E74: ESD 5285 | F74: Multicore Program Optimization Lab | G74: * | I74: * | J74: * | K74: * | L74: 73 | M74: MPO Lab | N74: Lab | O74: Active
A75: 2024 | B75: 2024-2025 | C75: 010I39 | D75: II | E75: BDA 5182 | F75: Principles of Data Visualization Lab | I75: * | K75: * | L75: 74 | N75: Lab
A76: 2024 | B76: 2024-2025 | C76: 010I39 | D76: II | E76: ESD 5282 | F76: IT Project Management Lab | G76: * | I76: * | K76: * | L76: 75 | N76: Lab
A77: 2024 | B77: 2024-2025 | C77: 010I39 | D77: II | E77: ESD 5283 | F77: Mobile Application Development using Android Lab | G77: * | I77: * | J77: * | K77: * | L77: 76 | N77: Lab
A78: 2024 | B78: 2024-2025 | C78: 010I39 | D78: II | E78: ESD 5051 | F78: Digital Signal Processing Lab | G78: * | I78: * | J78: * | L78: 77 | N78: Lab
A79: 2024 | B79: 2024-2025 | C79: 010I39 | D79: II | E79: ESD 5288 | F79: Virtual Prototyping Lab | G79: * | I79: * | J79: * | K79: * | L79: 78 | M79: VP Lab | N79: Lab | O79: Active
A80: 2024 | B80: 2024-2025 | C80: 010I39 | D80: II | E80: ESD 5287 | F80: Web Application Development Lab | G80: * | I80: * | L80: 79 | N80: Lab
A81: 2024 | B81: 2024-2025 | C81: 010I39 | D81: II | E81: ENP 5280 | F81: Entrepreneurship Lab | I81: * | J81: * | L81: 80 | N81: Lab
A82: 2024 | B82: 2024-2025 | C82: 010I39 | D82: II | E82: VLS 5051 | F82: High Level Digital Design Lab | I82: * | J82: * | K82: * | L82: 81 | N82: Lab
A83: 2024 | B83: 2024-2025 | C83: 010I39 | D83: II | E83: MPT 5200 | F83: Mini Project - II | G83: * | H83: * | I83: * | J83: * | K83: * | L83: 82 | M83: MP 2 | N83: Project | O83: Active
A84: 2024 | B84: 2024-2025 | C84: 010I39 | D84: II | E84: PSD 5200 | F84: Professional Skill Development - II | I84: * | J84: * | K84: * | L84: 83 | M84: PSD 2 | N84: Seminar | O84: Active
A85: 2024 | B85: 2024-2025 | C85: 010I39 | D85: III & IV | E85: ESD 6098 | F85: Project Work | G85: * | H85: * | I85: * | J85: * | K85: * | L85: 84 | N85: Project
A86: 2024 | B86: 2024-2025 | C86: 010I47 | D86: I | E86: CDC 5104 | F86: Linux and Data Structures | G86: * | I86: * | K86: * | L86: 85 | M86: LDS | N86: Theory | O86: Active
A87: 2024 | B87: 2024-2025 | C87: 010I47 | D87: I | E87: CDC 5001 | F87: DevOps for Cloud | G87: * | I87: * | J87: * | K87: * | L87: 86 | M87: Devops | N87: Theory | O87: Active
A88: 2024 | B88: 2024-2025 | C88: 010I47 | D88: I | E88: CDC 5102 | F88: Cloud Architecture and Management | G88: * | I88: * | J88: * | K88: * | L88: 87 | M88: CAM | N88: Theory | O88: Active
A89: 2024 | B89: 2024-2025 | C89: 010I47 | D89: I | E89: CDC 5101 | F89: Cloud Application with JAVA and Database with Java | G89: * | I89: * | J89: * | L89: 88 | M89: CAJD | N89: Theory | O89: Active
A90: 2024 | B90: 2024-2025 | C90: 010I47 | D90: I | E90: CDC 5131 | F90: Client-Side Internet Technology | G90: * | I90: * | J90: * | K90: * | L90: 89 | N90: Theory
A91: 2024 | B91: 2024-2025 | C91: 010I47 | D91: I | E91: BDA 5103 | F91: Fundamentals of Machine Learning | I91: * | J91: * | K91: * | L91: 90 | N91: Theory
A92: 2024 | B92: 2024-2025 | C92: 010I47 | D92: I | E92: CDC 5132 | F92: Cloud Foundations and Architecting | G92: * | I92: * | J92: * | K92: * | L92: 91 | M92: CFA | N92: Theory | O92: Active
A93: 2024 | B93: 2024-2025 | C93: 010I47 | D93: I | E93: CDC 5133 | F93: Cloud Administration and Solution Architect | G93: * | I93: * | J93: * | K93: * | L93: 92 | N93: Theory
A94: 2024 | B94: 2024-2025 | C94: 010I47 | D94: I | E94: CDC 5154 | F94: Linux and Data Structures Lab | G94: * | I94: * | K94: * | L94: 93 | M94: LDS Lab | N94: Lab | O94: Active
A95: 2024 | B95: 2024-2025 | C95: 010I47 | D95: I | E95: CDC 5051 | F95: DevOps for Cloud Lab | G95: * | I95: * | J95: * | K95: * | L95: 94 | M95: Devops Lab | N95: Lab | O95: Active
A96: 2024 | B96: 2024-2025 | C96: 010I47 | D96: I | E96: CDC 5152 | F96: Cloud Architecture and Management Lab | G96: * | I96: * | J96: * | K96: * | L96: 95 | M96: CAM Lab | N96: Lab | O96: Active
A97: 2024 | B97: 2024-2025 | C97: 010I47 | D97: I | E97: CDC 5151 | F97: Cloud Application with JAVA and Database Lab | G97: * | I97: * | J97: * | L97: 96 | M97: CAJD Lab | N97: Lab | O97: Active
A98: 2024 | B98: 2024-2025 | C98: 010I47 | D98: I | E98: CDC 5181 | F98: Client-Side Internet Technology Lab | G98: * | I98: * | J98: * | K98: * | L98: 97 | N98: Lab
A99: 2024 | B99: 2024-2025 | C99: 010I47 | D99: I | E99: BDA 5153 | F99: Fundamentals of Machine Learning Lab | I99: * | J99: * | K99: * | L99: 98 | N99: Lab
A100: 2024 | B100: 2024-2025 | C100: 010I47 | D100: I | E100: CDC 5182 | F100: Cloud Foundations and Architecting Lab | G100: * | I100: * | J100: * | K100: * | L100: 99 | M100: CFA Lab | N100: Lab | O100: Active
...

Sheet Faculty
A1: Faculty Master
A2: Faculty Short Code | B2: Faculty Code | C2: Faculty Name | D2: Signature
A3: BDR | B3: MAHE0004209 | C3: Dr. B Dinesh Rao | D3: #VALUE!
A4: PKS | B4: MAHE0004212 | C4: Dr. Prashanth Kumar Shetty | D4: #VALUE!
A5: SN | B5: MAHE0004783 | C5: Mr. Shridhar Nayak | D5: #VALUE!
A6: KP | B6: MAHE0004785 | C6: Dr. Keerthana Prasad | D6: #VALUE!
A7: DPK | B7: MAHE0004835 | C7: Dr. Deepak Rao | D7: #VALUE!
A8: SNM | B8: MAHE0004926 | C8: Dr. Sathyendranath Malli | D8: #VALUE!
A9: KB | B9: MAHE0007015 | C9: Ms. Keerthana B | D9: #VALUE!
A10: ARAJ | B10: MAHE0007066 | C10: Dr. Arockiaraj | D10: #VALUE!
A11: RK | B11: MAHE0007069 | C11: Ms. Ravikala Kamath | D11: #VALUE!
A12: RP | B12: MAHE0007611 | C12: Dr. Raghavendra Prabhu | D12: #VALUE!
A13: BB | B13: MAHE0008359 | C13: Mr. Balaji B | D13: #VALUE!
A14: MS | B14: MAHE0008403 | C14: Dr. Madhushankar Bhat | D14: #VALUE!
... A22: DP | B22: MAHE0026851 | C22: Dr. Devi Prasad M | D22: #VALUE!
A23: WB | B23: MAHE0028188 | C23: Mr. Winson Benedict Fernandes
A24: NM | B24: MAHE0028191 | C24: Ms. Nimisha | D24: #VALUE!
A25: RS | B25: MAHE0028454 | C25: Dr. Richa Sharma | D25: #VALUE!
A29: VSNS | B29: VF_010_04 | C29: Suchitra N Shenoy | D29: #VALUE!
A30: VJR | B30: GUEST004 | C30: Jyothsna Rai | D30: #VALUE!

Sheet TImetable
A1: Rooms | B1: Day | C1: Time | E1: Program Code | F1: Day | G1: Time | H1: Course SC | I1: Course Code | K1: Program | L1: Room
A2: LG01-LH02 | B2: Monday | C2: 8-9 | I2: {=IF(E2="","",_xlfn.XLOOKUP(E2&H2,Course!$A$2:$A$582&Course!$K$2:$K$582,Course!$C$2:$C$582,""))} | K2: 010I61 | L2: LG01-LH08
A3: LG01-LH08 | B3: Tuesday | C3: 9-10 | I3: {=IF(E3="","",_xlfn.XLOOKUP(E3&H3,Course!$A$2:$A$582&Course!$K$2:$K$582,Course!$C$2:$C$582,""))} | K3: 010I62 | L3: LG01-LH10
A4: LG01-LH10 | B4: Wednesday | C4: 10-11 | I4: {=IF(E4="","",_xlfn.XLOOKUP(E4&H4,Course!$A$2:$A$582&Course!$K$2:$K$582,Course!$C$2:$C$582,""))} | K4: 010I63 | L4: LG01-LH11
A5: LG01-LH11 | B5: Thursday | C5: 11-12 | I5: {=IF(E5="","",_xlfn.XLOOKUP(E5&H5,Course!$A$2:$A$582&Course!$K$2:$K$582,Course!$C$2:$C$582,""))} | K5: 010I64 | L5: LG01-LH11
A6: LG01-LH12 | B6: Friday | C6: 12-1 | I6: {=IF(E6="","",_xlfn.XLOOKUP(E6&H6,Course!$A$2:$A$582&Course!$K$2:$K$582,Course!$C$2:$C$582,""))} | K6: 010I65 | L6: LG01-LH09
A7: LG02-LH04 | B7: Saturday | C7: 1-2 | I7: {=IF(E7="","",_xlfn.XLOOKUP(E7&H7,Course!$A$2:$A$582&Course!$K$2:$K$582,Course!$C$2:$C$582,""))} | K7: 010I66 | L7: LG01-LH12
A8: LG01-LH09 | C8: 2-3 | I8: {=IF(E8="","",_xlfn.XLOOKUP(E8&H8,Course!$A$2:$A$582&Course!$K$2:$K$582,Course!$C$2:$C$582,""))} | K8: 010I67 | L8: LG01-LH08
A9: LG01-LH01 | C9: 3-4 | I9: {=IF(E9="","",_xlfn.XLOOKUP(E9&H9,Course!$A$2:$A$582&Course!$K$2:$K$582,Course!$C$2:$C$582,""))} | K9: 010I68 | L9: LG01-LH02
C10: 4-5 | I10: {=IF(E10="","",_xlfn.XLOOKUP(E10&H10,Course!$A$2:$A$582&Course!$K$2:$K$582,Course!$C$2:$C$582,""))} | K10: 010I69 | L10: LG01-LH01
I11: {=IF(E11="","",_xlfn.XLOOKUP(E11&H11,Course!$A$2:$A$582&Course!$K$2:$K$582,Course!$C$2:$C$582,""))}
I12: {=IF(E12="","",_xlfn.XLOOKUP(E12&H12,Course!$A$2:$A$582&Course!$K$2:$K$582,Course!$C$2:$C$582,""))}
I13: {=IF(E13="","",_xlfn.XLOOKUP(E13&H13,Course!$A$2:$A$582&Course!$K$2:$K$582,Course!$C$2:$C$582,""))}
I14: {=IF(E14="","",_xlfn.XLOOKUP(E14&H14,Course!$A$2:$A$582&Course!$K$2:$K$582,Course!$C$2:$C$582,""))}
I15: {=IF(E15="","",_xlfn.XLOOKUP(E15&H15,Course!$A$2:$A$582&Course!$K$2:$K$582,Course!$C$2:$C$582,""))}
I16: {=IF(E16="","",_xlfn.XLOOKUP(E16&H16,Course!$A$2:$A$582&Course!$K$2:$K$582,Course!$C$2:$C$582,""))}
I17: {=IF(E17="","",_xlfn.XLOOKUP(E17&H17,Course!$A$2:$A$582&Course!$K$2:$K$582,Course!$C$2:$C$582,""))}
I18: {=IF(E18="","",_xlfn.XLOOKUP(E18&H18,Course!$A$2:$A$582&Course!$K$2:$K$582,Course!$C$2:$C$582,""))}
I19: {=IF(E19="","",_xlfn.XLOOKUP(E19&H19,Course!$A$2:$A$582&Course!$K$2:$K$582,Course!$C$2:$C$582,""))}
I20: {=IF(E20="","",_xlfn.XLOOKUP(E20&H20,Course!$A$2:$A$582&Course!$K$2:$K$582,Course!$C$2:$C$582,""))}
I21: {=IF(E21="","",_xlfn.XLOOKUP(E21&H21,Course!$A$2:$A$582&Course!$K$2:$K$582,Course!$C$2:$C$582,""))}
I22: {=IF(E22="","",_xlfn.XLOOKUP(E22&H22,Course!$A$2:$A$582&Course!$K$2:$K$582,Course!$C$2:$C$582,""))}
... I500: {=IF(E500="","",_xlfn.XLOOKUP(E500&H500,Course!$A$2:$A$582&Course!$K$2:$K$582,Course!$C$2:$C$582,""))}

Sheet COs 24 & 25
A1: Academic Year | B1: Subject Type | C1: Subject Class | D1: Semester | E1: Program | F1: Subject Code | G1: Subject Name | H1: COs | I1: Course Outcome | J1: No. of Hours
A2: 2024-2025 | B2: Theory | C2: Core | D2: I | E2: 010I38 | F2: VLS 5001 | G2: High Level Digital Design | H2: CO1 | I2: Apply combination logic gates and arithmetic circuits
A3: 2024-2025 | B3: Theory | C3: Core | D3: I | E3: 010I38 | F3: VLS 5001 | G3: High Level Digital Design | H3: CO2 | I3: Analyze data path functional units and optimization
A4: 2024-2025 | B4: Theory | C4: Core | D4: I | E4: 010I38 | F4: VLS 5001 | G4: High Level Digital Design | H4: CO3 | I4: Analyze sequential logic and finite state machine circuits with timing aspect
A5: 2024-2025 | B5: Theory | C5: Core | D5: I | E5: 010I38 | F5: VLS 5001 | G5: High Level Digital Design | H5: CO4 | I5: Apply Field Programming Gate Arrays and First In First Out
A6: 2024-2025 | B6: Theory | C6: Core | D6: I | E6: 010I38 | F6: VLS 5001 | G6: High Level Digital Design | H6: CO5 | I6: Analyze AMBA bus architecture
A7: 2024-2025 | B7: Theory | C7: Core | D7: I | E7: 010I38 | F7: VLS 5101 | G7: Data Structures | H7: CO1 | I7: Design programs for implementation of linked lists, stack and queues.
A8: 2024-2025 | B8: Theory | C8: Core | D8: I | E8: 010I38 | F8: VLS 5101 | G8: Data Structures | H8: CO2 | I8: Design programs for implementation of binary search tree, sorting and searching, dictionary and Hash Table
A9: 2024-2025 | B9: Theory | C9: Core | D9: I | E9: 010I38 | F9: VLS 5101 | G9: Data Structures | H9: CO3 | I9: Design programs for graphs and shortest path techniques.
A10: 2024-2025 | B10: Theory | C10: Core | D10: I | E10: 010I38 | F10: VLS 5102 | G10: Digital Systems and VLSI Design | H10: CO1 | I10: Explain various CMOS process technologies and manufacturing issues.
A11: 2024-2025 | B11: Theory | C11: Core | D11: I | E11: 010I38 | F11: VLS 5102 | G11: Digital Systems and VLSI Design | H11: CO2 | I11: Analyze the static and dynamic behavior of MOSFETs and the secondary effects of the MOS transistor model.
A12: 2024-2025 | B12: Theory | C12: Core | D12: I | E12: 010I38 | F12: VLS 5102 | G12: Digital Systems and VLSI Design | H12: CO3 | I12: Design and test CMOS combinational and sequential logic at transistor level, including mask layout.
A13: 2024-2025 | B13: Theory | C13: Core | D13: I | E13: 010I38 | F13: VLS 5102 | G13: Digital Systems and VLSI Design | H13: CO4 | I13: Describe circuit characterization and manufacturing issues.
... A544: 2024-2025 | B544: Lab | C544: ELE 2 | D544: II | E544: 010I60 | F544: MVT 5281 | G544: IC Packaging Technology Lab | H544: CO3 | I544: Analyze three-dimensional integrated circuits packaging
A545: 2024-2025 | B545: Seminar | C545: Core | D545: I | F545: PSD 5100 | G545: Professional Skill Development - I | H545: CO1 | I545: Identify and synthesize important themes in the field of engineering which transform socio-economic ecosystem.
A546: 2024-2025 | B546: Seminar | C546: Core | D546: I | F546: PSD 5100 | G546: Professional Skill Development - I | H546: CO2 | I546: Develop competence to communicate effectively in oral and written forms.
A547: 2024-2025 | B547: Seminar | C547: Core | D547: I | F547: PSD 5100 | G547: Professional Skill Development - I | H547: CO3 | I547: Effective management of time, involve in reflective learning and adhere to the professional code of conduct.
A548: 2024-2025 | B548: Seminar | C548: Core | D548: II | F548: PSD 5100 | G548: Professional Skill Development - II | H548: CO1 | I548: Develop the skills needed for approaching technical and HR interviews.
A549: 2024-2025 | B549: Seminar | C549: Core | D549: II | F549: PSD 5100 | G549: Professional Skill Development - II | H549: CO2 | I549: Use mathematical, reasoning, and domain specific skills to solve objective questionnaires in time.
A550: 2024-2025 | B550: Seminar | C550: Core | D550: II | F550: PSD 5100 | G550: Professional Skill Development - II | H550: CO3 | I550: Demonstrate depth of knowledge in the chosen field of study.
A551: 2025-2026 | B551: Theory | C551: Core | D551: I | E551: 010I61 | F551: AME 5001 | G551: Applied Generative AI and Machine Learning | H551: CO1 | I551: Apply different types of supervised and unsupervised machine learning algorithms to practical problems. | J551: 12
A552: 2025-2026 | B552: Theory | C552: Core | D552: I | E552: 010I61 | F552: AME 5001 | G552: Applied Generative AI and Machine Learning | H552: CO2 | I552: Analyse different types of machine learning paradigms. | J552: 12
A553: 2025-2026 | B553: Theory | C553: Core | D553: I | E553: 010I61 | F553: AME 5001 | G553: Applied Generative AI and Machine Learning | H553: CO3 | I553: Effectively apply large language models for practical problems. | J553: 12
A554: 2025-2026 | B554: Theory | C554: Core | D554: I | E554: 010I61 | F554: BDE 5002 | G554: Principles of Data Visualization | H554: CO1 | I554: Implement web scraping techniques to extract data from websites. | J554: 9
A555: 2025-2026 | B555: Theory | C555: Core | D555: I | E555: 010I61 | F555: BDE 5002 | G555: Principles of Data Visualization | H555: CO2 | I555: Organize raw data for analysis using data manipulation techniques. | J555: 15
A556: 2025-2026 | B556: Theory | C556: Core | D556: I | E556: 010I61 | F556: BDE 5002 | G556: Principles of Data Visualization | H556: CO3 | I556: Interpret data using data visualization techniques. | J556: 12
A557: 2025-2026 | B557: Theory | C557: Core | D557: I | E557: 010I61 | F557: CCE 5101 | G557: Cloud Application with Java and Database | H557: CO1 | I557: Apply Java programming techniques and data interface concepts for application development. | J557: 16
A558: 2025-2026 | B558: Theory | C558: Core | D558: I | E558: 010I61 | F558: CCE 5101 | G558: Cloud Application with Java and Database | H558: CO2 | I558: Analyze the techniques to be used for high availability and fault tolerant cloud applications. | J558: 14
A559: 2025-2026 | B559: Theory | C559: Core | D559: I | E559: 010I61 | F559: CCE 5101 | G559: Cloud Application with Java and Database | H559: CO3 | I559: Understand the Cloud application architecture and design principles. | J559: 6
A560: 2025-2026 | B560: Theory | C560: Core | D560: I | E560: 010I61 | F560: ESE 5102 | G560: Data Structures and Algorithms | H560: CO1 | I560: Analyze the implementations of elementary data structures. | J560: 12
A561: 2025-2026 | B561: Theory | C561: Core | D561: I | E561: 010I61 | F561: ESE 5102 | G561: Data Structures and Algorithms | H561: CO2 | I561: Design and implementation of data structures like trees and graphs. | J561: 15
A562: 2025-2026 | B562: Theory | C562: Core | D562: I | E562: 010I61 | F562: ESE 5102 | G562: Data Structures and Algorithms | H562: CO3 | I562: Analyze the concepts of divide and conquer, dynamic programming, greedy, and back tracking techniques to efficiently solve problems. | J562: 9
... A601: 2025-2026 | B601: Theory | C601: ELE 1 | D601: II | E601: 010I61 | F601: CCE 5203 | G601: Cloud Security Essentials | H601: CO3 | I601: Examine logging and monitoring services to identify the incidence. | J601: 12
A602: 2025-2026 | B602: Theory | C602: ELE 1 | D602: II | E602: 010I61 | F602: ESE 5234 | G602: Entrepreneurship | H602: CO1 | I602: Explain the importance of entrepreneurship and entrepreneurial development model, social responsibilities of business.
A603: 2025-2026 | B603: Theory | C603: ELE 1 | D603: II | E603: 010I61 | F603: ESE 5234 | G603: Entrepreneurship | H603: CO2 | I603: Describe Entrepreneurial Traits and Factors affecting Entrepreneurship process.
A604: 2025-2026 | B604: Theory | C604: ELE 1 | D604: II | E604: 010I61 | F604: ESE 5234 | G604: Entrepreneurship | H604: CO3 | I604: Discuss Business Start-up Process.
A605: 2025-2026 | B605: Theory | C605: ELE 1 | D605: II | E605: 010I61 | F605: ESE 5234 | G605: Entrepreneurship | H605: CO4 | I605: Summarize a business and marketing plan for entrepreneurs.
A606: 2025-2026 | B606: Theory | C606: ELE 2 | D606: II | E606: 010I61 | F606: AME 5242 | G606: Natural Language Processing Principles and Applications | H606: CO1 | I606: Understand text processing for information extraction and retrieval. | J606: 10
A607: 2025-2026 | B607: Theory | C607: ELE 2 | D607: II | E607: 010I61 | F607: AME 5242 | G607: Natural Language Processing Principles and Applications | H607: CO2 | I607: Compare and contrast state-of-the-art word vectorization models for real-world problems. | J607: 12
A608: 2025-2026 | B608: Theory | C608: ELE 2 | D608: II | E608: 010I61 | F608: AME 5242 | G608: Natural Language Processing Principles and Applications | H608: CO3 | I608: Apply deep learning-based approaches for natural language processing tasks. | J608: 14
A609: 2025-2026 | B609: Theory | C609: ELE 2 | D609: II | E609: 010I61 | F609: CYE 5203 | G609: Machine Learning for Cybersecurity | H609: CO1 | I609: Demonstrate various data analytics and data visualization techniques for cybersecurity applications. | J609: 10
A610: 2025-2026 | B610: Theory | C610: ELE 2 | D610: II | E610: 010I61 | F610: CYE 5203 | G610: Machine Learning for Cybersecurity | H610: CO2 | I610: Implement and assess various machine learning models to detect and mitigate security threats. | J610: 15
A611: 2025-2026 | B611: Theory | C611: ELE 2 | D611: II | E611: 010I61 | F611: CYE 5203 | G611: Machine Learning for Cybersecurity | H611: CO3 | I611: Analyze adversarial machine learning techniques and generative AI for cybersecurity applications. | J611: 11
A612: 2025-2026 | B612: Theory | C612: ELE 2 | D612: II | E612: 010I61 | F612: CCE 5241 | G612: Cloud Operations | H612: CO1 | I612: Understand the architectural decisions and use cloud services to build decoupled serverless microservices. | J612: 10
A613: 2025-2026 | B613: Theory | C613: ELE 2 | D613: II | E613: 010I61 | F613: CCE 5241 | G613: Cloud Operations | H613: CO2 | I613: Analyze the tools specific to cloud operations engineer to create reusable compute and networking cloud infrastructures. | J613: 14
A614: 2025-2026 | B614: Theory | C614: ELE 2 | D614: II | E614: 010I61 | F614: CCE 5241 | G614: Cloud Operations | H614: CO3 | I614: Apply cloud architecting solutions to manage, automate, secure, and monitor highly available and fault tolerant infrastructures. | J614: 12
A615: 2025-2026 | B615: Theory | C615: ELE 2 | D615: II | E615: 010I61 | F615: ESE 5244 | G615: IT Project Management | H615: CO1 | I615: Illustrate the importance of project planning.
A616: 2025-2026 | B616: Theory | C616: ELE 2 | D616: II | E616: 010I61 | F616: ESE 5244 | G616: IT Project Management | H616: CO2 | I616: Discuss and demonstrate various tools applicable for different phases of the software project.
A617: 2025-2026 | B617: Theory | C617: ELE 2 | D617: II | E617: 010I61 | F617: ESE 5244 | G617: IT Project Management | H617: CO3 | I617: Illustrate the importance of Change management.
A618: 2025-2026 | B618: Theory | C618: ELE 2 | D618: II | E618: 010I61 | F618: ESE 5244 | G618: IT Project Management | H618: CO4 | I618: Illustrate the importance of team work and demonstrate the usefulness of tools in effective handling of the project.
A619: 2025-2026 | B619: Theory | C619: ELE 2 | D619: II | E619: 010I61 | F619: ESE 5244 | G619: IT Project Management | H619: CO5 | I619: Compare the problems in projects that don’t follow the process and discuss new trends in software life cycle.
A620: 2025-2026 | B620: Lab | C620: Core | D620: II | E620: 010I61 | F620: AME 5252 | G620: Deep Learning Lab | H620: CO1 | I620: Apply state-of-the-art deep learning tools and libraries. | J620: 12
A621: 2025-2026 | B621: Lab | C621: Core | D621: II | E621: 010I61 | F621: AME 5252 | G621: Deep Learning Lab | H621: CO2 | I621: Implement and investigate techniques for improving the way neural networks learn. | J621: 12
A622: 2025-2026 | B622: Lab | C622: Core | D622: II | E622: 010I61 | F622: AME 5252 | G622: Deep Learning Lab | H622: CO3 | I622: Apply and analyze deep learning models for real-world problems. | J622: 12
A623: 2025-2026 | B623: Lab | C623: Core | D623: II | E623: 010I61 | F623: BDE 5252 | G623: Modern Databases for Big Data Lab | H623: CO1 | I623: Apply the principles of relational database management. | J623: 12
A624: 2025-2026 | B624: Lab | C624: Core | D624: II | E624: 010I61 | F624: BDE 5252 | G624: Modern Databases for Big Data Lab | H624: CO2 | I624: Apply and evaluate different transaction processing and lock management methods. | J624: 12
A625: 2025-2026 | B625: Lab | C625: Core | D625: II | E625: 010I61 | F625: BDE 5252 | G625: Modern Databases for Big Data Lab | H625: CO3 | I625: Apply the principles of document DB and vector DB. | J625: 12
A626: 2025-2026 | B626: Lab | C626: Core | D626: II | E626: 010I61 | F626: ESE 5251 | G626: Device Drivers Lab | H626: CO1 | I626: Demonstrate the development of basic modules and drivers. | J626: 12
A627: 2025-2026 | B627: Lab | C627: Core | D627: II | E627: 010I61 | F627: ESE 5251 | G627: Device Drivers Lab | H627: CO2 | I627: Examine the ways of debugging and handling concurrency in device drivers. | J627: 12
A628: 2025-2026 | B628: Lab | C628: Core | D628: II | E628: 010I61 | F628: ESE 5251 | G628: Device Drivers Lab | H628: CO3 | I628: Examine the implementation of interrupts and work queues for deferred work. | J628: 12
A629: 2025-2026 | B629: Lab | C629: ELE 1 | D629: II | E629: 010I61 | F629: AME 5251 | G629: Convolutional Neural Networks for Computer Vision Lab | H629: CO1 | I629: Apply computer vision techniques and CNNs for problem solving. | J629: 12
A630: 2025-2026 | B630: Lab | C630: ELE 1 | D630: II | E630: 010I61 | F630: AME 5251 | G630: Convolutional Neural Networks for Computer Vision Lab | H630: CO2 | I630: Develop and design CNN architecture using the basic building blocks of CNN. | J630: 15
A631: 2025-2026 | B631: Lab | C631: ELE 1 | D631: II | E631: 010I61 | F631: AME 5251 | G631: Convolutional Neural Networks for Computer Vision Lab | H631: CO3 | I631: Investigate the use of existing CNN architecture for an application problem. | J631: 9
... A640: 2025-2026 | B640: Lab | C640: ELE 1 | D640: II | E640: 010I61 | F640: CCE 5253 | G640: Cloud Security Essentials Lab | H640: CO3 | I640: Develop an architecture for handling monitoring and incident response using AWS services. | J640: 12
A641: 2025-2026 | B641: Lab | C641: ELE 1 | D641: II | E641: 010I61 | F641: ESE 5284 | G641: Entrepreneurship Lab | H641: CO1 | I641: Study of prominence of entrepreneurship.
A642: 2025-2026 | B642: Lab | C642: ELE 1 | D642: II | E642: 010I61 | F642: ESE 5284 | G642: Entrepreneurship Lab | H642: CO2 | I642: Develop use cases for building a business.
A643: 2025-2026 | B643: Lab | C643: ELE 1 | D643: II | E643: 010I61 | F643: ESE 5284 | G643: Entrepreneurship Lab | H643: CO3 | I643: Evaluation of factors influencing business venture.
A644: 2025-2026 | B644: Lab | C644: ELE 2 | D644: II | E644: 010I61 | F644: AME 5292 | G644: Natural Language Processing Principles and Applications Lab | H644: CO1 | I644: Implement text processing techniques for information extraction & retrieval. | J644: 9
A645: 2025-2026 | B645: Lab | C645: ELE 2 | D645: II | E645: 010I61 | F645: AME 5292 | G645: Natural Language Processing Principles and Applications Lab | H645: CO2 | I645: Apply state-of-the-art word vectorization models for real-world problems. | J645: 12
A646: 2025-2026 | B646: Lab | C646: ELE 2 | D646: II | E646: 010I61 | F646: AME 5292 | G646: Natural Language Processing Principles and Applications Lab | H646: CO3 | I646: Formulate and apply deep learning-based approaches for natural language processing tasks. | J646: 15
A647: 2025-2026 | B647: Lab | C647: ELE 2 | D647: II | E647: 010I61 | F647: CYE 5253 | G647: Machine Learning for Cybersecurity Lab | H647: CO1 | I647: Apply data preprocessing, feature extraction, and visualization to detect cybersecurity threats. | J647: 12
A648: 2025-2026 | B648: Lab | C648: ELE 2 | D648: II | E648: 010I61 | F648: CYE 5253 | G648: Machine Learning for Cybersecurity Lab | H648: CO2 | I648: Implement and evaluate machine learning algorithms for intrusion detection and anomaly detection. | J648: 15
A649: 2025-2026 | B649: Lab | C649: ELE 2 | D649: II | E649: 010I61 | F649: CYE 5253 | G649: Machine Learning for Cybersecurity Lab | H649: CO3 | I649: Understand adversarial machine learning techniques and apply counter measures using AI-based security strategies. | J649: 9
A650: 2025-2026 | B650: Lab | C650: ELE 2 | D650: II | E650: 010I61 | F650: CCE 5291 | G650: Cloud Operations Lab | H650: CO1 | I650: Examine the architectural decisions and use cloud services to build decoupled serverless microservices. | J650: 12
A651: 2025-2026 | B651: Lab | C651: ELE 2 | D651: II | E651: 010I61 | F651: CCE 5291 | G651: Cloud Operations Lab | H651: CO2 | I651: Experiment the tools specific to cloud operations engineer to create reusable compute and networking cloud infrastructures. | J651: 12
A652: 2025-2026 | B652: Lab | C652: ELE 2 | D652: II | E652: 010I61 | F652: CCE 5291 | G652: Cloud Operations Lab | H652: CO3 | I652: Design cloud architecting solutions to manage, automate, secure, and monitor highly available and fault tolerant infrastructures. | J652: 12
A653: 2025-2026 | B653: Lab | C653: ELE 2 | D653: II | E653: 010I61 | F653: ESE 5294 | G653: IT Project Management Lab | H653: CO1 | I653: Identify the skills and techniques required for project life cycle. | J653: 12
A654: 2025-2026 | B654: Lab | C654: ELE 2 | D654: II | E654: 010I61 | F654: ESE 5294 | G654: IT Project Management Lab | H654: CO2 | I654: Illustrate essential principles associated with project management and their application in business environment. | J654: 12
A655: 2025-2026 | B655: Lab | C655: ELE 2 | D655: II | E655: 010I61 | F655: ESE 5294 | G655: IT Project Management Lab | H655: CO3 | I655: Outline commonly available project management tools. | J655: 12
... A694: 2025-2026 | B694: Theory | C694: Core | D694: II | E694: 010I62 | F694: ESE 5203 | G694: Multicore Program Optimization | H694: CO3 | I694: Demonstrate the development of multithreaded applications on multicore architectures. | J694: 10
A695: 2025-2026 | B695: Theory | C695: ELE 1 | D695: II | E695: 010I62 | F695: ESE 5231 | G695: Mobile Application Development using Android | H695: CO1 | I695: Distinguish the major building blocks of an android application.
A696: 2025-2026 | B696: Theory | C696: ELE 1 | D696: II | E696: 010I62 | F696: ESE 5231 | G696: Mobile Application Development using Android | H696: CO2 | I696: Organize an android application using various UI components
A697: 2025-2026 | B697: Theory | C697: ELE 1 | D697: II | E697: 010I62 | F697: ESE 5231 | G697: Mobile Application Development using Android | H697: CO3 | I697: Analyze the data handling android applications using SQLite
A698: 2025-2026 | B698: Theory | C698: ELE 1 | D698: II | E698: 010I62 | F698: ESE 5231 | G698: Mobile Application Development using Android | H698: CO4 | I698: Analyze the advanced topics such as LBS, Mapping, Network connectivity, background threads, adapters
A699: 2025-2026 | B699: Theory | C699: ELE 1 | D699: II | E699: 010I62 | F699: ESE 5232 | G699: Web Application Development | H699: CO1 | I699: Design a database and normalize the database.
A700: 2025-2026 | B700: Theory | C700: ELE 1 | D700: II | E700: 010I62 | F700: ESE 5232 | G700: Web Application Development | H700: CO2 | I700: Identify the appropriate types of data to be stored.
A701: 2025-2026 | B701: Theory | C701: ELE 1 | D701: II | E701: 010I62 | F701: ESE 5232 | G701: Web Application Development | H701: CO3 | I701: Develop a Web application using ASP.NET.
A702: 2025-2026 | B702: Theory | C702: ELE 1 | D702: II | E702: 010I62 | F702: ESE 5232 | G702: Web Application Development | H702: CO4 | I702: Recognize the need for Client-Server Architecture.
A703: 2025-2026 | B703: Theory | C703: ELE 1 | D703: II | E703: 010I62 | F703: ESE 5232 | G703: Web Application Development | H703: CO5 | I703: Construct a web page using HTML and CSS.
A704: 2025-2026 | B704: Theory | C704: ELE 1 | D704: II | E704: 010I62 | F704: BDE 5002 | G704: Principles of Data Visualization | H704: CO1 | I704: Implement web scraping techniques to extract data from websites. | J704: 9
A705: 2025-2026 | B705: Theory | C705: ELE 1 | D705: II | E705: 010I62 | F705: BDE 5002 | G705: Principles of Data Visualization | H705: CO2 | I705: Organize raw data for analysis using data manipulation techniques. | J705: 15
A706: 2025-2026 | B706: Theory | C706: ELE 1 | D706: II | E706: 010I62 | F706: BDE 5002 | G706: Principles of Data Visualization | H706: CO3 | I706: Interpret data using data visualization techniques. | J706: 12
A707: 2025-2026 | B707: Theory | C707: ELE 1 | D707: II | E707: 010I62 | F707: VDE 5232 | G707: System on Chip Design | H707: CO1 | I707: Apply electronic system level flow for system on chip design. | J707: 12
A708: 2025-2026 | B708: Theory | C708: ELE 1 | D708: II | E708: 010I62 | F708: VDE 5232 | G708: System on Chip Design | H708: CO2 | I708: Analyze robust processors and memory. | J708: 14
A709: 2025-2026 | B709: Theory | C709: ELE 1 | D709: II | E709: 010I62 | F709: VDE 5232 | G709: System on Chip Design | H709: CO3 | I709: Apply hardware interconnects, interfaces and applications. | J709: 10
A710: 2025-2026 | B710: Theory | C710: ELE 1 | D710: II | E710: 010I62 | F710: ESE 5234 | G710: Entrepreneurship | H710: CO1 | I710: Explain the importance of entrepreneurship and entrepreneurial development model, social responsibilities of business
A711: 2025-2026 | B711: Theory | C711: ELE 1 | D711: II | E711: 010I62 | F711: ESE 5234 | G711: Entrepreneurship | H711: CO2 | I711: Describe Entrepreneurial Traits and Factors affecting Entrepreneurship process
A712: 2025-2026 | B712: Theory | C712: ELE 1 | D712: II | E712: 010I62 | F712: ESE 5234 | G712: Entrepreneurship | H712: CO3 | I712: Discuss Business Start-up Process
A713: 2025-2026 | B713: Theory | C713: ELE 1 | D713: II | E713: 010I62 | F713: ESE 5234 | G713: Entrepreneurship | H713: CO4 | I713: Summarize a business and marketing plan for entrepreneurs.
A714: 2025-2026 | B714: Theory | C714: ELE 2 | D714: II | E714: 010I62 | F714: ESE 5241 | G714: Computer Networks | H714: CO1 | I714: Identify the goals and applications of computer networks, able to explain the classification of networks and reference models.
...

Sheet Rough Sheet
E5: Solving linear equations. | F5: CO1
E6: Applications in deep learning - Introduction to sensitivity and gradient in one dimension. | F6: CO3
E7: Chain rule. Matrix derivatives. | F7: CO3
E8: Gradient descent. | F8: CO2
E9: Training the artificical neural networks - backward propagation of errors. | F9: CO2
E10: Backpropagation algorithm. | F10: CO3
E11: Introduction to Attention mechanism. | F11: CO1
E12: Impementation details of attention mechanism in large language models. | F12: CO3
E13: Impementation details of attention mechanism in large language models. | F13: CO3
E14: Tensor cores and GPU architectures | F14: CO2
E15: Tensor cores and GPU architectures | F15: CO2

Sheet Setup
A1: Faculty Code (MAHE0xxxx) | B1: MAHE0026851 | C1: =IF(B5="","","COs of "&B5) -> COs of Applied Linear Algebra
A2: Faculty Name | B2: =IF(B1="","",IFERROR(VLOOKUP(B1,Faculty!$B$3:$C$40,2,0),"Invalid Faculty Code")) -> Dr. Devi Prasad M | C2: =IF($B$5="","","COs") -> COs | D2: =IF($B$5="","","Course Outcome") -> Course Outcome | E2: =IF($B$5="","","BL Mapping") -> BL Mapping | F2: =IF($B$5="","","1st PO") -> 1st PO | G2: =IF($B$5="","","2nd PO (If any)") -> 2nd PO (If any) | H2: =IF($B$5="","","3rd PO (If any)") -> 3rd PO (If any)
A3: Academic Year | B3: 2026-2027 | C3: {=IF(B5="","",_xlfn._xlws.FILTER(COs!$E$2:$F$1000,(COs!$A$2:$A$1000=B7)*(COs!$C$2:$C$1000=B8),""))} -> CO1 | D3: Apply vector operations for similarity learning. | E3: 3 | F3: PO3 | I3: =IF(AND(F3<>"",G3="",H3=""),F3,IF(AND(F3<>"",G3<>"",H3=""),F3&","&G3,IF(AND(F3<>"",G3<>"",H3<>""),F3&","&G3&","&H3,""))) -> PO3
A4: Program Name | B4: Master of Engineering – M.E in Computer Science and Engineering | C4: CO2 | D4: Analyse matrix representations in AI & ML models. | E4: 4 | F4: PO4 | G4: PO3 | I4: =IF(AND(F4<>"",G4="",H4=""),F4,IF(AND(F4<>"",G4<>"",H4=""),F4&","&G4,IF(AND(F4<>"",G4<>"",H4<>""),F4&","&G4&","&H4,""))) -> PO4,PO3
A5: Course Name | B5: Applied Linear Algebra | C5: CO3 | D5: Apply matrix calculus for optimization in learning systems. | E5: 3 | F5: PO3 | I5: =IF(AND(F5<>"",G5="",H5=""),F5,IF(AND(F5<>"",G5<>"",H5=""),F5&","&G5,IF(AND(F5<>"",G5<>"",H5<>""),F5&","&G5&","&H5,""))) -> PO3
A6: Semester | B6: Semester - I | I6: =IF(AND(F6<>"",G6="",H6=""),F6,IF(AND(F6<>"",G6<>"",H6=""),F6&","&G6,IF(AND(F6<>"",G6<>"",H6<>""),F6&","&G6&","&H6,"")))
A7: Program Code | B7: =IF(B4="","",_xlfn.XLOOKUP(B4,Program!$C$2:$C$50,Program!$B$2:$B$50,"")) -> 010I61 | I7: =IF(AND(F7<>"",G7="",H7=""),F7,IF(AND(F7<>"",G7<>"",H7=""),F7&","&G7,IF(AND(F7<>"",G7<>"",H7<>""),F7&","&G7&","&H7,"")))
A8: Course Code | B8: {=IF(B5="","",_xlfn.XLOOKUP(B7&B5,Course!$A$2:$A$500&Course!$D$2:$D$500,Course!$C$2:$C$500,""))} -> AME 5101
A9: Course Coordinator | B9: =IF(B2="","",B2) -> Dr. Devi Prasad M | C9: =IFERROR(VLOOKUP(B2,Faculty!$C$3:$D$100,2,0),"") -> #VALUE!
A10: Program Coordinator | B10: =IFERROR(VLOOKUP(IFERROR(VLOOKUP(B7,Program!$B$2:$D$50,3,0),""),Faculty!$A$3:$D$50,3,0),"") -> Dr. Sathyendranath Malli | C10: =IFERROR(VLOOKUP(B10,Faculty!$C$3:$D$100,2,0),"") -> #VALUE!
A11: Subject Type | B11: {=IF(B2="","",_xlfn.XLOOKUP(B7&B8,Course!$A$2:$A$500&Course!$C$2:$C$500,Course!$M$2:$M$500,""))} -> Core
A12: Sem | B12: =IF(B6="Semester - I","I","II") -> I

Sheet Lesson Plan
A1: =IF(Setup!$B$5="","","Lesson Plan of "&Setup!$B$5) -> Lesson Plan of Applied Linear Algebra
A2: =IF($A$1="","","S.No.") -> S.No. | B2: =IF($A$1="","","L.No.") -> L.No. | C2: =IF($A$1="","","TOPICS") -> TOPICS | D2: =IF($A$1="","","Course Outcome Addressed") -> Course Outcome Addressed | F2: =IF($A$1="","","COs") -> COs | G2: =IF($A$1="","","Expected No. of Hours") -> Expected No. of Hours | H2: =IF($A$1="","","Remaining No. of Hours") -> Remaining No. of Hours
A3: =IF($A$1="","",IF(Setup!B2="","",IF(C3="","",IF(C3="MID SEMESTER EXAM","MSE",0)))) -> 0 | B3: =IF($A$1="","",IF(Setup!B2="","",IF(A3="MSE","MSE",IF(A3="ESE","ESE","L"&A3)))) -> L0 | C3: =IF($A$1="","",IF(Setup!B2="","","Course delivery plan, Course assessment plan, Course outcomes, Program outcomes, CO-PO mapping, reference books.")) -> Course delivery plan, Course assessment plan, Course outcomes, Program outcomes, CO-PO mapping, reference books. | D3: =IF(A3="","","---") -> --- | F3: {=_xlfn._xlws.FILTER(Setup!$C$3:$C$7,Setup!$C$3:$C$7<>"","")} -> CO1 | G3: {=IF(F3="","",_xlfn.XLOOKUP(Setup!$B$7&Setup!$B$8&F3,COs!$A$2:$A$1000&COs!$C$2:$C$1000&COs!$E$2:$E$1000,COs!$G$2:$G$1000,""))} -> 10 | H3: =IF(F3="","",G3-COUNTIF('Lesson Plan - Sort'!$D$3:$D$50,F3)) -> 0
A4: =IF(C4="","",IF(C4="MID SEMESTER EXAM","MSE",1)) -> 1 | B4: =IF(A4="","",IF(A4="MSE","MSE",IF(A4="ESE","ESE","L"&A4))) -> L1 | C4: Conceptual introduction to vector spaces and vector operations. Scalar product. | D4: CO1 | F4: CO2 | G4: {=IF(F4="","",_xlfn.XLOOKUP(Setup!$B$7&Setup!$B$8&F4,COs!$A$2:$A$1000&COs!$C$2:$C$1000&COs!$E$2:$E$1000,COs!$G$2:$G$1000,""))} -> 14 | H4: =IF(F4="","",G4-COUNTIF('Lesson Plan - Sort'!$D$3:$D$50,F4)) -> 0
A5: =IF(C5="","",IF(C5="MID SEMESTER EXAM","MSE",IF(C5="END SEMESTER EXAM","ESE",IFERROR(A4+1,A3+1)))) -> 2 | B5: =IF(A5="","",IF(A5="MSE","MSE",IF(A5="ESE","ESE","L"&A5))) -> L2 | C5: Introduction to matrices. Types of matrices. Operations. Matric-vector multiplication. | D5: CO2 | F5: CO3 | G5: {=IF(F5="","",_xlfn.XLOOKUP(Setup!$B$7&Setup!$B$8&F5,COs!$A$2:$A$1000&COs!$C$2:$C$1000&COs!$E$2:$E$1000,COs!$G$2:$G$1000,""))} -> 12 | H5: =IF(F5="","",G5-COUNTIF('Lesson Plan - Sort'!$D$3:$D$50,F5)) -> 0
A6: =IF(C6="","",IF(C6="MID SEMESTER EXAM","MSE",IF(C6="END SEMESTER EXAM","ESE",IFERROR(A5+1,A4+1)))) -> 3 | B6: =IF(A6="","",IF(A6="MSE","MSE",IF(A6="ESE","ESE","L"&A6))) -> L3 | C6: Inner and outer products. Norm of a vector. Distance - standard deviation. Standardizations versus normalization. | D6: CO1 | G6: {=IF(F6="","",_xlfn.XLOOKUP(Setup!$B$7&Setup!$B$8&F6,COs!$A$2:$A$1000&COs!$C$2:$C$1000&COs!$E$2:$E$1000,COs!$G$2:$G$1000,""))} | H6: =IF(F6="","",G6-COUNTIF('Lesson Plan - Sort'!$D$3:$D$50,F6))
A7: =IF(C7="","",IF(C7="MID SEMESTER EXAM","MSE",IF(C7="END SEMESTER EXAM","ESE",IFERROR(A6+1,A5+1)))) -> 4 | B7: =IF(A7="","",IF(A7="MSE","MSE",IF(A7="ESE","ESE","L"&A7))) -> L4 | C7: Linear independence and basis vectors. | D7: CO2 | G7: {=IF(F7="","",_xlfn.XLOOKUP(Setup!$B$7&Setup!$B$8&F7,COs!$A$2:$A$1000&COs!$C$2:$C$1000&COs!$E$2:$E$1000,COs!$G$2:$G$1000,""))} | H7: =IF(F7="","",G7-COUNTIF('Lesson Plan - Sort'!$D$3:$D$50,F7))
A8: =IF(C8="","",IF(C8="MID SEMESTER EXAM","MSE",IF(C8="END SEMESTER EXAM","ESE",IFERROR(A7+1,A6+1)))) -> 5 | B8: =IF(A8="","",IF(A8="MSE","MSE",IF(A8="ESE","ESE","L"&A8))) -> L5 | C8: High-dimensional vector embeddings as in Word2Vec and LLMs. | D8: CO2 | F8: =IF($A$1="","","Total") -> Total | G8: =IF($A$1="","",SUM(G3:G7)) -> 36 | H8: =IF($A$1="","",SUM(H3:H7)) -> 0
A9: =IF(C9="","",IF(C9="MID SEMESTER EXAM","MSE",IF(C9="END SEMESTER EXAM","ESE",IFERROR(A8+1,A7+1)))) -> 6 | B9: =IF(A9="","",IF(A9="MSE","MSE",IF(A9="ESE","ESE","L"&A9))) -> L6 | C9: Linear operations on embeddings: Finding relationships, combining and isolating concepts, and analogies. | D9: CO1
A10: =IF(C10="","",IF(C10="MID SEMESTER EXAM","MSE",IF(C10="END SEMESTER EXAM","ESE",IFERROR(A9+1,A8+1)))) -> 7 | B10: =IF(A10="","",IF(A10="MSE","MSE",IF(A10="ESE","ESE","L"&A10))) -> L7 | C10: Systems of linear equations: over and under-determined systems. | D10: CO1
A11: =IF(C11="","",IF(C11="MID SEMESTER EXAM","MSE",IF(C11="END SEMESTER EXAM","ESE",IFERROR(A10+1,A9+1)))) -> 8 | B11: =IF(A11="","",IF(A11="MSE","MSE",IF(A11="ESE","ESE","L"&A11))) -> L8 | C11: Gram-Schmidt algorithm. | D11: CO3
A12: =IF(C12="","",IF(C12="MID SEMESTER EXAM","MSE",IF(C12="END SEMESTER EXAM","ESE",IFERROR(A11+1,A10+1)))) -> 9 | B12: =IF(A12="","",IF(A12="MSE","MSE",IF(A12="ESE","ESE","L"&A12))) -> L9 | C12: QR-factorization. | D12: CO2
A13: =IF(C13="","",IF(C13="MID SEMESTER EXAM","MSE",IF(C13="END SEMESTER EXAM","ESE",IFERROR(A12+1,A11+1)))) -> 10 | B13: =IF(A13="","",IF(A13="MSE","MSE",IF(A13="ESE","ESE","L"&A13))) -> L10 | C13: Solving linear equations. | D13: CO1
A14: =IF(C14="","",IF(C14="MID SEMESTER EXAM","MSE",IF(C14="END SEMESTER EXAM","ESE",IFERROR(A13+1,A12+1)))) -> 11 | B14: =IF(A14="","",IF(A14="MSE","MSE",IF(A14="ESE","ESE","L"&A14))) -> L11 | C14: Applications in deep learning - Introduction to sensitivity and gradient in one dimension. | D14: CO3
A15: =IF(C15="","",IF(C15="MID SEMESTER EXAM","MSE",IF(C15="END SEMESTER EXAM","ESE",IFERROR(A14+1,A13+1)))) -> 12 | B15: =IF(A15="","",IF(A15="MSE","MSE",IF(A15="ESE","ESE","L"&A15))) -> L12 | C15: Chain rule. Matrix derivatives. | D15: CO3
A16: =IF(C16="","",IF(C16="MID SEMESTER EXAM","MSE",IF(C16="END SEMESTER EXAM","ESE",IFERROR(A15+1,A14+1)))) -> 13 | B16: =IF(A16="","",IF(A16="MSE","MSE",IF(A16="ESE","ESE","L"&A16))) -> L13 | C16: Gradient descent. | D16: CO2
A17: =IF(C17="","",IF(C17="MID SEMESTER EXAM","MSE",IF(C17="END SEMESTER EXAM","ESE",IFERROR(A16+1,A15+1)))) -> 14 | B17: =IF(A17="","",IF(A17="MSE","MSE",IF(A17="ESE","ESE","L"&A17))) -> L14 | C17: Training the artificical neural networks - backward propagation of errors. | D17: CO2
A18: =IF(C18="","",IF(C18="MID SEMESTER EXAM","MSE",IF(C18="END SEMESTER EXAM","ESE",IFERROR(A17+1,A16+1)))) -> 15 | B18: =IF(A18="","",IF(A18="MSE","MSE",IF(A18="ESE","ESE","L"&A18))) -> L15 | C18: Backpropagation algorithm. | D18: CO3
A19: =IF('Rough Sheet'!F5="","",IF('Rough Sheet'!F5="MID SEMESTER EXAM","MSE",IF('Rough Sheet'!F5="END SEMESTER EXAM","ESE",IFERROR(A18+1,A17+1)))) -> 16 | B19: =IF(A19="","",IF(A19="MSE","MSE",IF(A19="ESE","ESE","L"&A19))) -> L16 | C19: Introduction to Attention mechanism. | D19: CO1
A20: =IF(C20="","",IF(C20="MID SEMESTER EXAM","MSE",IF(C20="END SEMESTER EXAM","ESE",IFERROR(A19+1,A18+1)))) -> 17 | B20: =IF(A20="","",IF(A20="MSE","MSE",IF(A20="ESE","ESE","L"&A20))) -> L17 | C20: Impementation details of attention mechanism in large language models. | D20: CO3
A21: =IF(C21="","",IF(C21="MID SEMESTER EXAM","MSE",IF(C21="END SEMESTER EXAM","ESE",IFERROR(A20+1,A19+1)))) -> 18 | B21: =IF(A21="","",IF(A21="MSE","MSE",IF(A21="ESE","ESE","L"&A21))) -> L18 | C21: Impementation details of attention mechanism in large language models. | D21: CO3
A22: =IF(C22="","",IF(C22="MID SEMESTER EXAM","MSE",IF(C22="END SEMESTER EXAM","ESE",IFERROR(A21+1,A20+1)))) -> 19 | B22: =IF(A22="","",IF(A22="MSE","MSE",IF(A22="ESE","ESE","L"&A22))) -> L19 | C22: Tensor cores and GPU architectures | D22: CO2
A23: =IF(C23="","",IF(C23="MID SEMESTER EXAM","MSE",IF(C23="END SEMESTER EXAM","ESE",IFERROR(A22+1,A21+1)))) -> 20 | B23: =IF(A23="","",IF(A23="MSE","MSE",IF(A23="ESE","ESE","L"&A23))) -> L20 | C23: Tensor cores and GPU architectures | D23: CO2
A24: =IF(C24="","",IF(C24="MID SEMESTER EXAM","MSE",IF(C24="END SEMESTER EXAM","ESE",IFERROR(A23+1,A22+1)))) -> 21 | B24: =IF(A24="","",IF(A24="MSE","MSE",IF(A24="ESE","ESE","L"&A24))) -> L21 | C24: Least squares: problem motivation and examples. | D24: CO2
A25: =IF(C25="","",IF(C25="MID SEMESTER EXAM","MSE",IF(C25="END SEMESTER EXAM","ESE",IFERROR(A24+1,A23+1)))) -> 22 | B25: =IF(A25="","",IF(A25="MSE","MSE",IF(A25="ESE","ESE","L"&A25))) -> L22 | C25: Solving least squares problems - least square data fitting. | D25: CO1
A26: =IF(C26="","",IF(C26="MID SEMESTER EXAM","MSE",IF(C26="END SEMESTER EXAM","ESE",IFERROR(A25+1,A24+1)))) -> 23 | B26: =IF(A26="","",IF(A26="MSE","MSE",IF(A26="ESE","ESE","L"&A26))) -> L23 | C26: Solving least squares problems - least square data fitting. | D26: CO3
A27: =IF(C27="","",IF(C27="MID SEMESTER EXAM","MSE",IF(C27="END SEMESTER EXAM","ESE",IFERROR(A26+1,A25+1)))) -> 24 | B27: =IF(A27="","",IF(A27="MSE","MSE",IF(A27="ESE","ESE","L"&A27))) -> L24 | C27: Maximizing variance and minimizing projection error. | D27: CO1
A28: =IF(C28="","",IF(C28="MID SEMESTER EXAM","MSE",IF(C28="END SEMESTER EXAM","ESE",IFERROR(A27+1,A26+1)))) -> 25 | B28: =IF(A28="","",IF(A28="MSE","MSE",IF(A28="ESE","ESE","L"&A28))) -> L25 | C28: Minimizing projection error, and identifying principal components visually. | D28: CO3
A29: =IF(C29="","",IF(C29="MID SEMESTER EXAM","MSE",IF(C29="END SEMESTER EXAM","ESE",IFERROR(A28+1,A27+1)))) -> 26 | B29: =IF(A29="","",IF(A29="MSE","MSE",IF(A29="ESE","ESE","L"&A29))) -> L26 | C29: Mean centering and covariance matrices. | D29: CO2
A30: =IF(C30="","",IF(C30="MID SEMESTER EXAM","MSE",IF(C30="END SEMESTER EXAM","ESE",IFERROR(A29+1,A28+1)))) -> 27 | B30: =IF(A30="","",IF(A30="MSE","MSE",IF(A30="ESE","ESE","L"&A30))) -> L27 | C30: Covariance matrices, eigenvectors, and eigenvalues. | D30: CO3
A31: =IF(C31="","",IF(C31="MID SEMESTER EXAM","MSE",IF(C31="END SEMESTER EXAM","ESE",IFERROR(A30+1,A29+1)))) -> 28 | B31: =IF(A31="","",IF(A31="MSE","MSE",IF(A31="ESE","ESE","L"&A31))) -> L28 | C31: Mean centering, covariance matrices, eigenvectors, and eigenvalues - Data Preparation and Relations. | D31: CO3
... A39: =IF(C39="","",IF(C39="MID SEMESTER EXAM","MSE",IF(C39="END SEMESTER EXAM","ESE",IFERROR(A38+1,A37+1)))) -> 36 | B39: =IF(A39="","",IF(A39="MSE","MSE",IF(A39="ESE","ESE","L"&A39))) -> L36 | C39: Linear/Identity activation functions at the output layer and Mean Squared Error (MSE) loss. Comparing gradient behavior and scale stability between regression and classification losses | D39: CO2
A40: =IF(C40="","",IF(C40="MID SEMESTER EXAM","MSE",IF(C40="END SEMESTER EXAM","ESE",IFERROR(A39+1,A38+1)))) | B40: =IF(A40="","",IF(A40="MSE","MSE",IF(A40="ESE","ESE","L"&A40)))
A41: =IF(C41="","",IF(C41="MID SEMESTER EXAM","MSE",IF(C41="END SEMESTER EXAM","ESE",IFERROR(A40+1,A39+1)))) | B41: =IF(A41="","",IF(A41="MSE","MSE",IF(A41="ESE","ESE","L"&A41)))
A42: =IF(C42="","",IF(C42="MID SEMESTER EXAM","MSE",IF(C42="END SEMESTER EXAM","ESE",IFERROR(A41+1,A40+1)))) | B42: =IF(A42="","",IF(A42="MSE","MSE",IF(A42="ESE","ESE","L"&A42)))
A43: =IF(C43="","",IF(C43="MID SEMESTER EXAM","MSE",IF(C43="END SEMESTER EXAM","ESE",IFERROR(A42+1,A41+1)))) | B43: =IF(A43="","",IF(A43="MSE","MSE",IF(A43="ESE","ESE","L"&A43)))
A44: =IF(C44="","",IF(C44="MID SEMESTER EXAM","MSE",IF(C44="END SEMESTER EXAM","ESE",IFERROR(A43+1,A42+1)))) | B44: =IF(A44="","",IF(A44="MSE","MSE",IF(A44="ESE","ESE","L"&A44)))
A45: =IF(C45="","",IF(C45="MID SEMESTER EXAM","MSE",IF(C45="END SEMESTER EXAM","ESE",IFERROR(A44+1,A43+1)))) | B45: =IF(A45="","",IF(A45="MSE","MSE",IF(A45="ESE","ESE","L"&A45)))
A46: =IF(C46="","",IF(C46="MID SEMESTER EXAM","MSE",IF(C46="END SEMESTER EXAM","ESE",IFERROR(A45+1,A44+1)))) | B46: =IF(A46="","",IF(A46="MSE","MSE",IF(A46="ESE","ESE","L"&A46)))
A47: =IF(C47="","",IF(C47="MID SEMESTER EXAM","MSE",IF(C47="END SEMESTER EXAM","ESE",IFERROR(A46+1,A45+1)))) | B47: =IF(A47="","",IF(A47="MSE","MSE",IF(A47="ESE","ESE","L"&A47)))
A48: =IF(C48="","",IF(C48="MID SEMESTER EXAM","MSE",IF(C48="END SEMESTER EXAM","ESE",IFERROR(A47+1,A46+1)))) | B48: =IF(A48="","",IF(A48="MSE","MSE",IF(A48="ESE","ESE","L"&A48)))
A49: =IF(C49="","",IF(C49="MID SEMESTER EXAM","MSE",IF(C49="END SEMESTER EXAM","ESE",IFERROR(A48+1,A47+1)))) | B49: =IF(A49="","",IF(A49="MSE","MSE",IF(A49="ESE","ESE","L"&A49)))
A50: =IF(C50="","",IF(C50="MID SEMESTER EXAM","MSE",IF(C50="END SEMESTER EXAM","ESE",IFERROR(A49+1,A48+1)))) | B50: =IF(A50="","",IF(A50="MSE","MSE",IF(A50="ESE","ESE","L"&A50)))

Sheet Lesson Plan - Sort
A1: ="Lesson Plan of "&Setup!B5 -> Lesson Plan of Applied Linear Algebra
A2: L. No. | B2: TOPICS | C2: Course Outcome Addressed | D2: COs without MSE & ESE
A3: {=_xlfn._xlws.FILTER('Lesson Plan'!$B$3:$D$50,'Lesson Plan'!$A$3:$A$50<>"","")} -> L0 | B3: Course delivery plan, Course assessment plan, Course outcomes, Program outcomes, CO-PO mapping, reference books. | C3: --- | D3: {=_xlfn._xlws.FILTER('Lesson Plan'!$D$3:$D$50,('Lesson Plan'!$A$3:$A$50<>"")*('Lesson Plan'!$A$3:$A$50<>"MSE")*('Lesson Plan'!$A$3:$A$50<>"ESE"),"")} -> ---
A4: L1 | B4: Conceptual introduction to vector spaces and vector operations. Scalar product. | C4: CO1 | D4: CO1
A5: L2 | B5: Introduction to matrices. Types of matrices. Operations. Matric-vector multiplication. | C5: CO2 | D5: CO2
A6: L3 | B6: Inner and outer products. Norm of a vector. Distance - standard deviation. Standardizations versus normalization. | C6: CO1 | D6: CO1
A7: L4 | B7: Linear independence and basis vectors. | C7: CO2 | D7: CO2
A8: L5 | B8: High-dimensional vector embeddings as in Word2Vec and LLMs. | C8: CO2 | D8: CO2
A9: L6 | B9: Linear operations on embeddings: Finding relationships, combining and isolating concepts, and analogies. | C9: CO1 | D9: CO1
A10: L7 | B10: Systems of linear equations: over and under-determined systems. | C10: CO1 | D10: CO1
A11: L8 | B11: Gram-Schmidt algorithm. | C11: CO3 | D11: CO3
A12: L9 | B12: QR-factorization. | C12: CO2 | D12: CO2
A13: L10 | B13: Solving linear equations. | C13: CO1 | D13: CO1
A14: L11 | B14: Applications in deep learning - Introduction to sensitivity and gradient in one dimension. | C14: CO3 | D14: CO3
A15: L12 | B15: Chain rule. Matrix derivatives. | C15: CO3 | D15: CO3
... A39: L36 | B39: Linear/Identity activation functions at the output layer and Mean Squared Error (MSE) loss. Comparing gradient behavior and scale stability between regression and classification losses | C39: CO2 | D39: CO2

Sheet Course Plan
A1: =IF(Setup!B5="","",IF(Setup!B4="","",Setup!B4)) -> Master of Engineering – M.E in Computer Science and Engineering
A2: =IF(A1="","","Course Plan") -> Course Plan
B4: =IF(A1="","","Course Name") -> Course Name | H4: =IF($B$4="","",":") -> : | I4: =IF($B$4="","",IF(Setup!B5="","",Setup!B5)) -> Applied Linear Algebra
B5: =IF(B4="","","Course Code") -> Course Code | H5: =IF($B$4="","",":") -> : | I5: =IF($B$4="","",IF(Setup!B8="","",Setup!B8)) -> AME 5101
B6: =IF(B4="","","Academic Year") -> Academic Year | H6: =IF($B$4="","",":") -> : | I6: =IF($B$4="","",IF(Setup!B3="","",Setup!B3)) -> 2026-2027
B7: =IF(B4="","","Semester") -> Semester | H7: =IF($B$4="","",":") -> : | I7: =IF($B$4="","",IF(Setup!B5="","",IF(Setup!B6="Semester - I","I","II"))) -> I
B8: =IF(B4="","","Name of the Course Coordinator") -> Name of the Course Coordinator | H8: =IF($B$4="","",":") -> : | I8: =IF($B$4="","",IF(Setup!B9="","",Setup!B9)) -> Dr. Devi Prasad M
B9: =IF(B4="","","Name of the Program Coordinator") -> Name of the Program Coordinator | H9: =IF($B$4="","",":") -> : | I9: =IF($B$4="","",IF(Setup!B4="","",Setup!B10)) -> Dr. Sathyendranath Malli
B12: =IF(SUM($O$170:$P$174)<>100,"",IF('E-Sign'!$C$5=TRUE,Setup!$C$10,"")) -> #VALUE! | L12: =IF(SUM($O$170:$P$174)<>100,"",IF('E-Sign'!$C$4=TRUE,Setup!$C$9,"")) -> #VALUE!
B14: =IF($B$4="","","Date:") -> Date: | E14: 46303 | L14: =IF($B$4="","","Date:") -> Date: | O14: 46303
B15: =IF($B$4="","","Signature of Program Coordinator") -> Signature of Program Coordinator | L15: =IF($B$4="","","Signature of Course Coordinator") -> Signature of Course Coordinator
B16: =IF($B$4="","","with Date") -> with Date | L16: =IF($B$4="","","with Date") -> with Date
B22: =IF($B$4="","","Table of Contents") -> Table of Contents
B23: =IF($B$4="","","1 Course Plan") -> 1 Course Plan | R23: =IF($B$4="","",5) -> 5
B24: =IF($B$4="",""," 1.1 Primary Information") -> 1.1 Primary Information | R24: =IF($B$4="","",5) -> 5
B25: =IF($B$4="",""," 1.2 Course Outcomes (COs), Program outcomes (POs) and Bloom’s Taxonomy Mapping") -> 1.2 Course Outcomes (COs), Program outcomes (POs) and Bloom’s Taxonomy Mapping | R25: =IF($B$4="","",6) -> 6
B26: =IF($B$4="",""," 1.3 Assessment Plan") -> 1.3 Assessment Plan | R26: =IF($B$4="","",7) -> 7
B27: =IF($B$4="",""," 1.4 Lesson Plan") -> 1.4 Lesson Plan | R27: =IF($B$4="","",8) -> 8
B28: =IF($B$4="",""," 1.5 References") -> 1.5 References | R28: =IF($B$4="","",11) -> 11
B29: =IF($B$4="",""," 1.6 Other Resources (Online, Text, Multimedia, etc.)") -> 1.6 Other Resources (Online, Text, Multimedia, etc.) | R29: =IF($B$4="","",11) -> 11
B30: =IF($B$4="",""," 1.7 Course Timetable") -> 1.7 Course Timetable | R30: =IF($B$4="","",12) -> 12
B31: =IF($B$4="",""," 1.8 Assessment Plan") -> 1.8 Assessment Plan | R31: =IF($B$4="","",13) -> 13
B32: =IF($B$4="",""," 1.9 Assessment Details") -> 1.9 Assessment Details | R32: =IF($B$4="","",15) -> 15
B33: =IF($B$4="",""," 1.10 Course Articulation Matrix") -> 1.10 Course Articulation Matrix | R33: =IF($B$4="","",16) -> 16
A43: =IF($B$4="","","Program Education Objectives (PEOs)") -> Program Education Objectives (PEOs)
A44: =IF($B$4="","","The overall objectives of the Learning Outcomes-based Curriculum Framework (LOCF) for "&Setup!B4&", programare as follows") -> The overall objectives of the Learning Outcomes-based Curriculum Framework (LOCF) for Master of Engineering – M.E in Computer Science and Engineering, programare as follows
A45: =IF($B$4="","","PEO No.") -> PEO No. | B45: =IF($B$4="","","Education Objective") -> Education Objective
A46: =IF($I$4="","",IF(PEOs!E3="","",PEOs!E3)) -> PEO 1 | B46: =IF($I$4="","",IF(PEOs!F3="","",PEOs!F3)) -> Enable to draw upon fundamental and advanced knowledge to apply analytical and computational approaches to solve technological problems in computer science.
A47: =IF($I$4="","",IF(PEOs!E4="","",PEOs!E4)) -> PEO 2 | B47: =IF($I$4="","",IF(PEOs!F4="","",PEOs!F4)) -> Introduce state of art technologies in computer science and inculcate ethical practices to make industry-ready professionals.
A48: =IF($I$4="","",IF(PEOs!E5="","",PEOs!E5)) -> PEO 3 | B48: =IF($I$4="","",IF(PEOs!F5="","",PEOs!F5)) -> Promote scientific and societal advancement through research and entrepreneurship.
A49: =IF($I$4="","",IF(PEOs!E6="","",PEOs!E6)) | B49: =IF($I$4="","",IF(PEOs!F6="","",PEOs!F6))
A50: =IF($I$4="","",IF(PEOs!E7="","",PEOs!E7)) | B50: =IF($I$4="","",IF(PEOs!F7="","",PEOs!F7))
A51: =IF($I$4="","",IF(PEOs!E8="","",PEOs!E8)) | B51: =IF($I$4="","",IF(PEOs!F8="","",PEOs!F8))
A52: =IF($I$4="","",IF(PEOs!E9="","",PEOs!E9)) | B52: =IF($I$4="","",IF(PEOs!F9="","",PEOs!F9))
A53: =IF($I$4="","",IF(PEOs!E10="","",PEOs!E10)) | B53: =IF($I$4="","",IF(PEOs!F10="","",PEOs!F10))
A56: =IF($B$4="","","Program Outcomes (POs)") -> Program Outcomes (POs)
A57: =IF($B$4="","","By the end of the postgraduate program in " &Setup!B4&", graduates will be able to:") -> By the end of the postgraduate program in Master of Engineering – M.E in Computer Science and Engineering, graduates will be able to:
A58: =IF($I$4="","",IF(POs!I3="","",POs!I3)) -> PO 1 | B58: =IF($I$4="","",IF(POs!J3="","",POs!J3)) -> An ability to independently carry out research /investigation and development work to solve practical problems.
A59: =IF($I$4="","",IF(POs!I4="","",POs!I4)) -> PO 2 | B59: =IF($I$4="","",IF(POs!J4="","",POs!J4)) -> An ability to write and present a substantial technical report/document.
A60: =IF($I$4="","",IF(POs!I5="","",POs!I5)) -> PO 3 | B60: =IF($I$4="","",IF(POs!J5="","",POs!J5)) -> An ability to demonstrate a degree of mastery over the area as per the specialization of the program. The mastery should be at a level higher than the requirements in the appropriate bachelor program.
A61: =IF($I$4="","",IF(POs!I6="","",POs!I6)) -> PO 4 | B61: =IF($I$4="","",IF(POs!J6="","",POs!J6)) -> An ability to develop software based on theoretical principles and practical knowledge.
A62: =IF($I$4="","",IF(POs!I7="","",POs!I7)) -> PO 5 | B62: =IF($I$4="","",IF(POs!J7="","",POs!J7)) -> An ability to demonstrate knowledge of the underlying principles and evaluation methods for analysing and decision-making.
A63: =IF($I$4="","",IF(POs!I8="","",POs!I8)) | B63: =IF($I$4="","",IF(POs!J8="","",POs!J8))
A64: =IF($I$4="","",IF(POs!I9="","",POs!I9)) | B64: =IF($I$4="","",IF(POs!J9="","",POs!J9))
A65: =IF($I$4="","",IF(POs!I10="","",POs!I10)) | B65: =IF($I$4="","",IF(POs!J10="","",POs!J10))
A68: =IF($B$4="","","1. Course Plan") -> 1. Course Plan
A69: =IF($B$4="","","1.1 Primary Information") -> 1.1 Primary Information
B71: =IF($B$4="","","Course Name") -> Course Name | I71: =IF($B$4="","",":") -> : | J71: =IF($B$4="","",Setup!B5&" ["&Setup!B8&"]") -> Applied Linear Algebra [AME 5101]
B72: =IF($B$4="","","L-T-P-C") -> L-T-P-C | I72: =IF($B$4="","",":") -> : | J72: =IF($B$4="","","3-0-0-3") -> 3-0-0-3
B73: =IF($B$4="","","Contact Hours") -> Contact Hours | I73: =IF($B$4="","",":") -> : | J73: =IF($B$4="","","36 Hours") -> 36 Hours
B74: =IF($B$4="","","Pre-requisite") -> Pre-requisite | I74: =IF($B$4="","",":") -> : | J74: Basic Algebra and Ca;culus
B75: =IF($B$4="","","Core/ PE/OE") -> Core/ PE/OE | I75: =IF($B$4="","",":") -> : | J75: =IF($B$4="","",IF(Setup!B11="Core","Core","PE")) -> Core
A77: =IF($B$4="","","1.2 Course Outcomes (COs), Program outcomes (POs) and Bloom’s Taxonomy Mapping") -> 1.2 Course Outcomes (COs), Program outcomes (POs) and Bloom’s Taxonomy Mapping
A79: =IF($B$4="","","CO") -> CO | B79: =IF($B$4="","","At the end of this course, the student should be able to:") -> At the end of this course, the student should be able to: | O79: =IF($B$4="","","No.ofContactHours") -> No.ofContactHours | Q79: =IF($B$4="","","Program Outcomes (POs)") -> Program Outcomes (POs) | S79: =IF($B$4="","","BL") -> BL
A80: =IF(Setup!C3="","",Setup!C3) -> CO1 | B80: =IF(Setup!D3="","",Setup!D3) -> Apply vector operations for similarity learning. | O80: =IF(A80="","",COUNTIF('Lesson Plan - Sort'!$D$3:$D$50,A80)) -> 10 | Q80: =IF(Setup!I3="","",Setup!I3) -> PO3 | S80: =IF(Setup!E3="","",Setup!E3) -> 3
A81: =IF(Setup!C4="","",Setup!C4) -> CO2 | B81: =IF(Setup!D4="","",Setup!D4) -> Analyse matrix representations in AI & ML models. | O81: =IF(A81="","",COUNTIF('Lesson Plan - Sort'!$D$3:$D$50,A81)) -> 14 | Q81: =IF(Setup!I4="","",Setup!I4) -> PO4,PO3 | S81: =IF(Setup!E4="","",Setup!E4) -> 4
A82: =IF(Setup!C5="","",Setup!C5) -> CO3 | B82: =IF(Setup!D5="","",Setup!D5) -> Apply matrix calculus for optimization in learning systems. | O82: =IF(A82="","",COUNTIF('Lesson Plan - Sort'!$D$3:$D$50,A82)) -> 12 | Q82: =IF(Setup!I5="","",Setup!I5) -> PO3 | S82: =IF(Setup!E5="","",Setup!E5) -> 3
A83: =IF(Setup!C6="","",Setup!C6) | B83: =IF(Setup!D6="","",Setup!D6) | O83: =IF(A83="","",COUNTIF('Lesson Plan - Sort'!$D$3:$D$50,A83)) | Q83: =IF(Setup!I6="","",Setup!I6) | S83: =IF(Setup!E6="","",Setup!E6)
A84: =IF(Setup!C7="","",Setup!C7) | B84: =IF(Setup!D7="","",Setup!D7) | O84: =IF(A84="","",COUNTIF('Lesson Plan - Sort'!$D$3:$D$50,A84)) | Q84: =IF(Setup!I7="","",Setup!I7) | S84: =IF(Setup!E7="","",Setup!E7)
A86: =IF($B$4="","","1.3 Assessment Plan") -> 1.3 Assessment Plan
A88: =IF($B$4="","","Components") -> Components | C88: =IF($B$4="","","Mid semester exam (MSE)") -> Mid semester exam (MSE) | I88: =IF($B$4="","","Flexible assessments") -> Flexible assessments | O88: =IF($B$4="","","End semester exam (ESE) / Makeup exam") -> End semester exam (ESE) / Makeup exam
A89: =IF($B$4="","","Duration") -> Duration | C89: =IF($B$4="","","90 minutes") -> 90 minutes | I89: 2 assignments. 15 days each. | O89: =IF($B$4="","","180 minutes") -> 180 minutes
A90: =IF($B$4="","","Weightage") -> Weightage | C90: =IF($B$4="","",0.3) -> 0.3 | I90: =IF($B$4="","",0.2) -> 0.2 | O90: =IF($B$4="","",0.5) -> 0.5
A91: =IF($B$4="","","Typology of questions") -> Typology of questions | C91: Applying and Analyzing | I91: Applying and Analyzing | O91: Applying and Analyzing
A92: =IF($B$4="","","Pattern") -> Pattern | C92: Answer all 5 questions of 10 marks each. Each question may have 2 parts of equal marks. | I92: Apply and analyze solutions to real-world problems. | O92: Answer all 10 questions of 10 marks each. Each question may have 2 parts of equal marks.
A93: =IF($B$4="","","Schedule") -> Schedule | C93: =IF($B$4="","","As per academic calendar.") -> As per academic calendar. | I93: September 15 and October 10 | O93: =IF($B$4="","","As per academic calendar.") -> As per academic calendar.
A94: =IF($B$4="","","Topics covered") -> Topics covered | C94: Vectos, matrics, GPU/TPU support for deep learning systems. | I94: Vectors, matrices, efficient solutions on GPU/TPUs. | O94: =IF($B$4="","","Comprehensive examination covering the full syllabus. Students are expected to answer all questions.") -> Comprehensive examination covering the full syllabus. Students are expected to answer all questions.
A97: =IF($B$4="","","1.4 Lesson Plan") -> 1.4 Lesson Plan
A98: =IF($B$4="","","L. No.") -> L. No. | B98: =IF($B$4="","","TOPICS") -> TOPICS | Q98: =IF($B$4="","","Course Outcome Addressed") -> Course Outcome Addressed
A99: {=_xlfn._xlws.FILTER('Lesson Plan - Sort'!$A$3:$A$50,'Lesson Plan - Sort'!$A$3:$A$50<>"","")} -> L0 | B99: =IF(A99="","",IFERROR(VLOOKUP(A99,'Lesson Plan - Sort'!$A$3:$C$50,2,0),"Contact Office")) -> Course delivery plan, Course assessment plan, Course outcomes, Program outcomes, CO-PO mapping, reference books. | Q99: =IF(A99="","",IFERROR(VLOOKUP(A99,'Lesson Plan - Sort'!$A$3:$C$50,3,0),"Contact Office")) -> ---
A100: L1 | B100: =IF(A100="","",IFERROR(VLOOKUP(A100,'Lesson Plan - Sort'!$A$3:$C$50,2,0),"Contact Office")) -> Conceptual introduction to vector spaces and vector operations. Scalar product. | Q100: =IF(A100="","",IFERROR(VLOOKUP(A100,'Lesson Plan - Sort'!$A$3:$C$50,3,0),"Contact Office")) -> CO1
A101: L2 | B101: =IF(A101="","",IFERROR(VLOOKUP(A101,'Lesson Plan - Sort'!$A$3:$C$50,2,0),"Contact Office")) -> Introduction to matrices. Types of matrices. Operations. Matric-vector multiplication. | Q101: =IF(A101="","",IFERROR(VLOOKUP(A101,'Lesson Plan - Sort'!$A$3:$C$50,3,0),"Contact Office")) -> CO2
A102: L3 | B102: =IF(A102="","",IFERROR(VLOOKUP(A102,'Lesson Plan - Sort'!$A$3:$C$50,2,0),"Contact Office")) -> Inner and outer products. Norm of a vector. Distance - standard deviation. Standardizations versus normalization. | Q102: =IF(A102="","",IFERROR(VLOOKUP(A102,'Lesson Plan - Sort'!$A$3:$C$50,3,0),"Contact Office")) -> CO1
A103: L4 | B103: =IF(A103="","",IFERROR(VLOOKUP(A103,'Lesson Plan - Sort'!$A$3:$C$50,2,0),"Contact Office")) -> Linear independence and basis vectors. | Q103: =IF(A103="","",IFERROR(VLOOKUP(A103,'Lesson Plan - Sort'!$A$3:$C$50,3,0),"Contact Office")) -> CO2
A104: L5 | B104: =IF(A104="","",IFERROR(VLOOKUP(A104,'Lesson Plan - Sort'!$A$3:$C$50,2,0),"Contact Office")) -> High-dimensional vector embeddings as in Word2Vec and LLMs. | Q104: =IF(A104="","",IFERROR(VLOOKUP(A104,'Lesson Plan - Sort'!$A$3:$C$50,3,0),"Contact Office")) -> CO2
A105: L6 | B105: =IF(A105="","",IFERROR(VLOOKUP(A105,'Lesson Plan - Sort'!$A$3:$C$50,2,0),"Contact Office")) -> Linear operations on embeddings: Finding relationships, combining and isolating concepts, and analogies. | Q105: =IF(A105="","",IFERROR(VLOOKUP(A105,'Lesson Plan - Sort'!$A$3:$C$50,3,0),"Contact Office")) -> CO1
A106: L7 | B106: =IF(A106="","",IFERROR(VLOOKUP(A106,'Lesson Plan - Sort'!$A$3:$C$50,2,0),"Contact Office")) -> Systems of linear equations: over and under-determined systems. | Q106: =IF(A106="","",IFERROR(VLOOKUP(A106,'Lesson Plan - Sort'!$A$3:$C$50,3,0),"Contact Office")) -> CO1
A107: L8 | B107: =IF(A107="","",IFERROR(VLOOKUP(A107,'Lesson Plan - Sort'!$A$3:$C$50,2,0),"Contact Office")) -> Gram-Schmidt algorithm. | Q107: =IF(A107="","",IFERROR(VLOOKUP(A107,'Lesson Plan - Sort'!$A$3:$C$50,3,0),"Contact Office")) -> CO3
A108: L9 | B108: =IF(A108="","",IFERROR(VLOOKUP(A108,'Lesson Plan - Sort'!$A$3:$C$50,2,0),"Contact Office")) -> QR-factorization. | Q108: =IF(A108="","",IFERROR(VLOOKUP(A108,'Lesson Plan - Sort'!$A$3:$C$50,3,0),"Contact Office")) -> CO2
A109: L10 | B109: =IF(A109="","",IFERROR(VLOOKUP(A109,'Lesson Plan - Sort'!$A$3:$C$50,2,0),"Contact Office")) -> Solving linear equations. | Q109: =IF(A109="","",IFERROR(VLOOKUP(A109,'Lesson Plan - Sort'!$A$3:$C$50,3,0),"Contact Office")) -> CO1
A110: L11 | B110: =IF(A110="","",IFERROR(VLOOKUP(A110,'Lesson Plan - Sort'!$A$3:$C$50,2,0),"Contact Office")) -> Applications in deep learning - Introduction to sensitivity and gradient in one dimension. | Q110: =IF(A110="","",IFERROR(VLOOKUP(A110,'Lesson Plan - Sort'!$A$3:$C$50,3,0),"Contact Office")) -> CO3
A111: L12 | B111: =IF(A111="","",IFERROR(VLOOKUP(A111,'Lesson Plan - Sort'!$A$3:$C$50,2,0),"Contact Office")) -> Chain rule. Matrix derivatives. | Q111: =IF(A111="","",IFERROR(VLOOKUP(A111,'Lesson Plan - Sort'!$A$3:$C$50,3,0),"Contact Office")) -> CO3
... A135: L36 | B135: =IF(A135="","",IFERROR(VLOOKUP(A135,'Lesson Plan - Sort'!$A$3:$C$50,2,0),"Contact Office")) -> Linear/Identity activation functions at the output layer and Mean Squared Error (MSE) loss. Comparing gradient behavior and scale stability between regression and classification losses | Q135: =IF(A135="","",IFERROR(VLOOKUP(A135,'Lesson Plan - Sort'!$A$3:$C$50,3,0),"Contact Office")) -> CO2
B136: =IF(A136="","",IFERROR(VLOOKUP(A136,'Lesson Plan - Sort'!$A$3:$C$50,2,0),"Contact Office")) | Q136: =IF(A136="","",IFERROR(VLOOKUP(A136,'Lesson Plan - Sort'!$A$3:$C$50,3,0),"Contact Office"))
B137: =IF(A137="","",IFERROR(VLOOKUP(A137,'Lesson Plan - Sort'!$A$3:$C$50,2,0),"Contact Office")) | Q137: =IF(A137="","",IFERROR(VLOOKUP(A137,'Lesson Plan - Sort'!$A$3:$C$50,3,0),"Contact Office"))
B138: =IF(A138="","",IFERROR(VLOOKUP(A138,'Lesson Plan - Sort'!$A$3:$C$50,2,0),"Contact Office")) | Q138: =IF(A138="","",IFERROR(VLOOKUP(A138,'Lesson Plan - Sort'!$A$3:$C$50,3,0),"Contact Office"))
B139: =IF(A139="","",IFERROR(VLOOKUP(A139,'Lesson Plan - Sort'!$A$3:$C$50,2,0),"Contact Office")) | Q139: =IF(A139="","",IFERROR(VLOOKUP(A139,'Lesson Plan - Sort'!$A$3:$C$50,3,0),"Contact Office"))
A141: =IF($B$4="","","1.5 References") -> 1.5 References
A142: {=IF($B$4="","",_xlfn.XLOOKUP(Setup!B7&Setup!B8,References!$A$2:$A$500&References!$C$2:$C$500,References!$E$2:$E$500,""))} -> 1. Introduction to Applied Linear Algebra, Vectors, Matrices, and Least Squares, Stephen Boyd & Lieven Vandenberghe, Cambridge University Press, 1st Edition, 2018. Available online at http://vmls-book.stanford.edu/vmls.pdf. 2. Linear Algebra and Learning from Data, Gilbert Strang, Cambridge Uni. Press, 1st Edition, 2019. 3. IBM AI Engineering Professional Certificate (https://www.coursera.org/professional- certificates/ai-engineer). 4. Deep Learning with Python, François Chollet, Manning Publications, 2nd Edition, 2021. 5. Neural Networks and Deep Learning, Michael A. Nielsen, Determination Press, 2015. Available online at http://neuralnetworksanddeeplearning.com/ 6. Matrix Methods: Applied Linear Algebra, Richard Bronson and Gabriel B. Costa, Academic Press, 3rd Edition, 2008. 7. Introduction to computational thinking (https://computationalthinking.mit.edu/Fall24/).
A143: =IF($B$4="","","1.6 Other Resources (Online, Text, Multimedia, etc.)") -> 1.6 Other Resources (Online, Text, Multimedia, etc.)
A144: =IF($B$4="","","1. Web Resources: Blog, Online tools and cloud resources. 2. Journal Articles.") -> 1. Web Resources: Blog, Online tools and cloud resources. 2. Journal Articles.
A147: =IF($B$4="","","1.7 Course Timetable") -> 1.7 Course Timetable
A149: =IF($B$4="","",I7&" Semester") -> I Semester | M149: =IF($B$4="","","Room:") -> Room: | Q149: =IFERROR(VLOOKUP(Setup!B7,TImetable!$K$2:$L$13,2,0),"") -> LG01-LH08
C150: =IF($B$4="","","8-9") -> 8-9 | E150: =IF($B$4="","","9-10") -> 9-10 | G150: =IF($B$4="","","10-11") -> 10-11 | I150: =IF($B$4="","","11-12") -> 11-12 | K150: =IF($B$4="","","12-1") -> 12-1 | M150: =IF($B$4="","","1-2") -> 1-2 | O150: =IF($B$4="","","2-3") -> 2-3 | Q150: =IF($B$4="","","3-4") -> 3-4 | S150: =IF($B$4="","","4-5") -> 4-5
A151: =IF($B$4="","","Monday") -> Monday | C151: {=IF($B$4="","",_xlfn.XLOOKUP(C$150&$A151&Setup!$B$7&Setup!$B$8,TImetable!$G$2:$G$500&TImetable!$F$2:$F$500&TImetable!$E$2:$E$500&TImetable!$I$2:$I$500,TImetable!$H$2:$H$500,""))} | E151: ALA | G151: {=IF($B$4="","",_xlfn.XLOOKUP(G$150&$A151&Setup!$B$7&Setup!$B$8,TImetable!$G$2:$G$500&TImetable!$F$2:$F$500&TImetable!$E$2:$E$500&TImetable!$I$2:$I$500,TImetable!$H$2:$H$500,""))} | I151: {=IF($B$4="","",_xlfn.XLOOKUP(I$150&$A151&Setup!$B$7&Setup!$B$8,TImetable!$G$2:$G$500&TImetable!$F$2:$F$500&TImetable!$E$2:$E$500&TImetable!$I$2:$I$500,TImetable!$H$2:$H$500,""))} | K151: {=IF($B$4="","",_xlfn.XLOOKUP(K$150&$A151&Setup!$B$7&Setup!$B$8,TImetable!$G$2:$G$500&TImetable!$F$2:$F$500&TImetable!$E$2:$E$500&TImetable!$I$2:$I$500,TImetable!$H$2:$H$500,""))} | M151: {=IF($B$4="","",_xlfn.XLOOKUP(M$150&$A151&Setup!$B$7&Setup!$B$8,TImetable!$G$2:$G$500&TImetable!$F$2:$F$500&TImetable!$E$2:$E$500&TImetable!$I$2:$I$500,TImetable!$H$2:$H$500,""))} | O151: {=IF($B$4="","",_xlfn.XLOOKUP(O$150&$A151&Setup!$B$7&Setup!$B$8,TImetable!$G$2:$G$500&TImetable!$F$2:$F$500&TImetable!$E$2:$E$500&TImetable!$I$2:$I$500,TImetable!$H$2:$H$500,""))} | Q151: {=IF($B$4="","",_xlfn.XLOOKUP(Q$150&$A151&Setup!$B$7&Setup!$B$8,TImetable!$G$2:$G$500&TImetable!$F$2:$F$500&TImetable!$E$2:$E$500&TImetable!$I$2:$I$500,TImetable!$H$2:$H$500,""))} | S151: {=IF($B$4="","",_xlfn.XLOOKUP(S$150&$A151&Setup!$B$7&Setup!$B$8,TImetable!$G$2:$G$500&TImetable!$F$2:$F$500&TImetable!$E$2:$E$500&TImetable!$I$2:$I$500,TImetable!$H$2:$H$500,""))}
A152: =IF($B$4="","","Tuesday") -> Tuesday | C152: {=IF($B$4="","",_xlfn.XLOOKUP(C$150&$A152&Setup!$B$7&Setup!$B$8,TImetable!$G$2:$G$500&TImetable!$F$2:$F$500&TImetable!$E$2:$E$500&TImetable!$I$2:$I$500,TImetable!$H$2:$H$500,""))} | E152: {=IF($B$4="","",_xlfn.XLOOKUP(E$150&$A152&Setup!$B$7&Setup!$B$8,TImetable!$G$2:$G$500&TImetable!$F$2:$F$500&TImetable!$E$2:$E$500&TImetable!$I$2:$I$500,TImetable!$H$2:$H$500,""))} | G152: {=IF($B$4="","",_xlfn.XLOOKUP(G$150&$A152&Setup!$B$7&Setup!$B$8,TImetable!$G$2:$G$500&TImetable!$F$2:$F$500&TImetable!$E$2:$E$500&TImetable!$I$2:$I$500,TImetable!$H$2:$H$500,""))} | I152: {=IF($B$4="","",_xlfn.XLOOKUP(I$150&$A152&Setup!$B$7&Setup!$B$8,TImetable!$G$2:$G$500&TImetable!$F$2:$F$500&TImetable!$E$2:$E$500&TImetable!$I$2:$I$500,TImetable!$H$2:$H$500,""))} | K152: {=IF($B$4="","",_xlfn.XLOOKUP(K$150&$A152&Setup!$B$7&Setup!$B$8,TImetable!$G$2:$G$500&TImetable!$F$2:$F$500&TImetable!$E$2:$E$500&TImetable!$I$2:$I$500,TImetable!$H$2:$H$500,""))} | M152: {=IF($B$4="","",_xlfn.XLOOKUP(M$150&$A152&Setup!$B$7&Setup!$B$8,TImetable!$G$2:$G$500&TImetable!$F$2:$F$500&TImetable!$E$2:$E$500&TImetable!$I$2:$I$500,TImetable!$H$2:$H$500,""))} | O152: {=IF($B$4="","",_xlfn.XLOOKUP(O$150&$A152&Setup!$B$7&Setup!$B$8,TImetable!$G$2:$G$500&TImetable!$F$2:$F$500&TImetable!$E$2:$E$500&TImetable!$I$2:$I$500,TImetable!$H$2:$H$500,""))} | Q152: {=IF($B$4="","",_xlfn.XLOOKUP(Q$150&$A152&Setup!$B$7&Setup!$B$8,TImetable!$G$2:$G$500&TImetable!$F$2:$F$500&TImetable!$E$2:$E$500&TImetable!$I$2:$I$500,TImetable!$H$2:$H$500,""))} | S152: {=IF($B$4="","",_xlfn.XLOOKUP(S$150&$A152&Setup!$B$7&Setup!$B$8,TImetable!$G$2:$G$500&TImetable!$F$2:$F$500&TImetable!$E$2:$E$500&TImetable!$I$2:$I$500,TImetable!$H$2:$H$500,""))}
A153: =IF($B$4="","","Wednesday") -> Wednesday | C153: {=IF($B$4="","",_xlfn.XLOOKUP(C$150&$A153&Setup!$B$7&Setup!$B$8,TImetable!$G$2:$G$500&TImetable!$F$2:$F$500&TImetable!$E$2:$E$500&TImetable!$I$2:$I$500,TImetable!$H$2:$H$500,""))} | E153: ALA | G153: {=IF($B$4="","",_xlfn.XLOOKUP(G$150&$A153&Setup!$B$7&Setup!$B$8,TImetable!$G$2:$G$500&TImetable!$F$2:$F$500&TImetable!$E$2:$E$500&TImetable!$I$2:$I$500,TImetable!$H$2:$H$500,""))} | I153: {=IF($B$4="","",_xlfn.XLOOKUP(I$150&$A153&Setup!$B$7&Setup!$B$8,TImetable!$G$2:$G$500&TImetable!$F$2:$F$500&TImetable!$E$2:$E$500&TImetable!$I$2:$I$500,TImetable!$H$2:$H$500,""))} | K153: {=IF($B$4="","",_xlfn.XLOOKUP(K$150&$A153&Setup!$B$7&Setup!$B$8,TImetable!$G$2:$G$500&TImetable!$F$2:$F$500&TImetable!$E$2:$E$500&TImetable!$I$2:$I$500,TImetable!$H$2:$H$500,""))} | M153: {=IF($B$4="","",_xlfn.XLOOKUP(M$150&$A153&Setup!$B$7&Setup!$B$8,TImetable!$G$2:$G$500&TImetable!$F$2:$F$500&TImetable!$E$2:$E$500&TImetable!$I$2:$I$500,TImetable!$H$2:$H$500,""))} | O153: {=IF($B$4="","",_xlfn.XLOOKUP(O$150&$A153&Setup!$B$7&Setup!$B$8,TImetable!$G$2:$G$500&TImetable!$F$2:$F$500&TImetable!$E$2:$E$500&TImetable!$I$2:$I$500,TImetable!$H$2:$H$500,""))} | Q153: {=IF($B$4="","",_xlfn.XLOOKUP(Q$150&$A153&Setup!$B$7&Setup!$B$8,TImetable!$G$2:$G$500&TImetable!$F$2:$F$500&TImetable!$E$2:$E$500&TImetable!$I$2:$I$500,TImetable!$H$2:$H$500,""))} | S153: {=IF($B$4="","",_xlfn.XLOOKUP(S$150&$A153&Setup!$B$7&Setup!$B$8,TImetable!$G$2:$G$500&TImetable!$F$2:$F$500&TImetable!$E$2:$E$500&TImetable!$I$2:$I$500,TImetable!$H$2:$H$500,""))}
A154: =IF($B$4="","","Thursday") -> Thursday | C154: {=IF($B$4="","",_xlfn.XLOOKUP(C$150&$A154&Setup!$B$7&Setup!$B$8,TImetable!$G$2:$G$500&TImetable!$F$2:$F$500&TImetable!$E$2:$E$500&TImetable!$I$2:$I$500,TImetable!$H$2:$H$500,""))} | E154: {=IF($B$4="","",_xlfn.XLOOKUP(E$150&$A154&Setup!$B$7&Setup!$B$8,TImetable!$G$2:$G$500&TImetable!$F$2:$F$500&TImetable!$E$2:$E$500&TImetable!$I$2:$I$500,TImetable!$H$2:$H$500,""))} | G154: {=IF($B$4="","",_xlfn.XLOOKUP(G$150&$A154&Setup!$B$7&Setup!$B$8,TImetable!$G$2:$G$500&TImetable!$F$2:$F$500&TImetable!$E$2:$E$500&TImetable!$I$2:$I$500,TImetable!$H$2:$H$500,""))} | I154: {=IF($B$4="","",_xlfn.XLOOKUP(I$150&$A154&Setup!$B$7&Setup!$B$8,TImetable!$G$2:$G$500&TImetable!$F$2:$F$500&TImetable!$E$2:$E$500&TImetable!$I$2:$I$500,TImetable!$H$2:$H$500,""))} | K154: {=IF($B$4="","",_xlfn.XLOOKUP(K$150&$A154&Setup!$B$7&Setup!$B$8,TImetable!$G$2:$G$500&TImetable!$F$2:$F$500&TImetable!$E$2:$E$500&TImetable!$I$2:$I$500,TImetable!$H$2:$H$500,""))} | M154: {=IF($B$4="","",_xlfn.XLOOKUP(M$150&$A154&Setup!$B$7&Setup!$B$8,TImetable!$G$2:$G$500&TImetable!$F$2:$F$500&TImetable!$E$2:$E$500&TImetable!$I$2:$I$500,TImetable!$H$2:$H$500,""))} | O154: {=IF($B$4="","",_xlfn.XLOOKUP(O$150&$A154&Setup!$B$7&Setup!$B$8,TImetable!$G$2:$G$500&TImetable!$F$2:$F$500&TImetable!$E$2:$E$500&TImetable!$I$2:$I$500,TImetable!$H$2:$H$500,""))} | Q154: {=IF($B$4="","",_xlfn.XLOOKUP(Q$150&$A154&Setup!$B$7&Setup!$B$8,TImetable!$G$2:$G$500&TImetable!$F$2:$F$500&TImetable!$E$2:$E$500&TImetable!$I$2:$I$500,TImetable!$H$2:$H$500,""))} | S154: {=IF($B$4="","",_xlfn.XLOOKUP(S$150&$A154&Setup!$B$7&Setup!$B$8,TImetable!$G$2:$G$500&TImetable!$F$2:$F$500&TImetable!$E$2:$E$500&TImetable!$I$2:$I$500,TImetable!$H$2:$H$500,""))}
A155: =IF($B$4="","","Friday") -> Friday | C155: {=IF($B$4="","",_xlfn.XLOOKUP(C$150&$A155&Setup!$B$7&Setup!$B$8,TImetable!$G$2:$G$500&TImetable!$F$2:$F$500&TImetable!$E$2:$E$500&TImetable!$I$2:$I$500,TImetable!$H$2:$H$500,""))} | E155: ALA | G155: {=IF($B$4="","",_xlfn.XLOOKUP(G$150&$A155&Setup!$B$7&Setup!$B$8,TImetable!$G$2:$G$500&TImetable!$F$2:$F$500&TImetable!$E$2:$E$500&TImetable!$I$2:$I$500,TImetable!$H$2:$H$500,""))} | I155: {=IF($B$4="","",_xlfn.XLOOKUP(I$150&$A155&Setup!$B$7&Setup!$B$8,TImetable!$G$2:$G$500&TImetable!$F$2:$F$500&TImetable!$E$2:$E$500&TImetable!$I$2:$I$500,TImetable!$H$2:$H$500,""))} | K155: {=IF($B$4="","",_xlfn.XLOOKUP(K$150&$A155&Setup!$B$7&Setup!$B$8,TImetable!$G$2:$G$500&TImetable!$F$2:$F$500&TImetable!$E$2:$E$500&TImetable!$I$2:$I$500,TImetable!$H$2:$H$500,""))} | M155: {=IF($B$4="","",_xlfn.XLOOKUP(M$150&$A155&Setup!$B$7&Setup!$B$8,TImetable!$G$2:$G$500&TImetable!$F$2:$F$500&TImetable!$E$2:$E$500&TImetable!$I$2:$I$500,TImetable!$H$2:$H$500,""))} | O155: {=IF($B$4="","",_xlfn.XLOOKUP(O$150&$A155&Setup!$B$7&Setup!$B$8,TImetable!$G$2:$G$500&TImetable!$F$2:$F$500&TImetable!$E$2:$E$500&TImetable!$I$2:$I$500,TImetable!$H$2:$H$500,""))} | Q155: {=IF($B$4="","",_xlfn.XLOOKUP(Q$150&$A155&Setup!$B$7&Setup!$B$8,TImetable!$G$2:$G$500&TImetable!$F$2:$F$500&TImetable!$E$2:$E$500&TImetable!$I$2:$I$500,TImetable!$H$2:$H$500,""))} | S155: {=IF($B$4="","",_xlfn.XLOOKUP(S$150&$A155&Setup!$B$7&Setup!$B$8,TImetable!$G$2:$G$500&TImetable!$F$2:$F$500&TImetable!$E$2:$E$500&TImetable!$I$2:$I$500,TImetable!$H$2:$H$500,""))}
A156: =IF($B$4="","","Saturday") -> Saturday | C156: {=IF($B$4="","",_xlfn.XLOOKUP(C$150&$A156&Setup!$B$7&Setup!$B$8,TImetable!$G$2:$G$500&TImetable!$F$2:$F$500&TImetable!$E$2:$E$500&TImetable!$I$2:$I$500,TImetable!$H$2:$H$500,""))} | E156: {=IF($B$4="","",_xlfn.XLOOKUP(E$150&$A156&Setup!$B$7&Setup!$B$8,TImetable!$G$2:$G$500&TImetable!$F$2:$F$500&TImetable!$E$2:$E$500&TImetable!$I$2:$I$500,TImetable!$H$2:$H$500,""))} | G156: {=IF($B$4="","",_xlfn.XLOOKUP(G$150&$A156&Setup!$B$7&Setup!$B$8,TImetable!$G$2:$G$500&TImetable!$F$2:$F$500&TImetable!$E$2:$E$500&TImetable!$I$2:$I$500,TImetable!$H$2:$H$500,""))} | I156: {=IF($B$4="","",_xlfn.XLOOKUP(I$150&$A156&Setup!$B$7&Setup!$B$8,TImetable!$G$2:$G$500&TImetable!$F$2:$F$500&TImetable!$E$2:$E$500&TImetable!$I$2:$I$500,TImetable!$H$2:$H$500,""))} | K156: {=IF($B$4="","",_xlfn.XLOOKUP(K$150&$A156&Setup!$B$7&Setup!$B$8,TImetable!$G$2:$G$500&TImetable!$F$2:$F$500&TImetable!$E$2:$E$500&TImetable!$I$2:$I$500,TImetable!$H$2:$H$500,""))} | M156: {=IF($B$4="","",_xlfn.XLOOKUP(M$150&$A156&Setup!$B$7&Setup!$B$8,TImetable!$G$2:$G$500&TImetable!$F$2:$F$500&TImetable!$E$2:$E$500&TImetable!$I$2:$I$500,TImetable!$H$2:$H$500,""))} | O156: {=IF($B$4="","",_xlfn.XLOOKUP(O$150&$A156&Setup!$B$7&Setup!$B$8,TImetable!$G$2:$G$500&TImetable!$F$2:$F$500&TImetable!$E$2:$E$500&TImetable!$I$2:$I$500,TImetable!$H$2:$H$500,""))} | Q156: {=IF($B$4="","",_xlfn.XLOOKUP(Q$150&$A156&Setup!$B$7&Setup!$B$8,TImetable!$G$2:$G$500&TImetable!$F$2:$F$500&TImetable!$E$2:$E$500&TImetable!$I$2:$I$500,TImetable!$H$2:$H$500,""))} | S156: {=IF($B$4="","",_xlfn.XLOOKUP(S$150&$A156&Setup!$B$7&Setup!$B$8,TImetable!$G$2:$G$500&TImetable!$F$2:$F$500&TImetable!$E$2:$E$500&TImetable!$I$2:$I$500,TImetable!$H$2:$H$500,""))}
...

Sheet E-Sign
C3: Declaration
C4: TRUE | D4: =IF(Setup!B9="","","I, "&Setup!B9&", hereby declare that the information provided is true and accurate to the best of my knowledge. I acknowledge that my electronic signature constitutes formal authentication of this declaration") -> I, Dr. Devi Prasad M, hereby declare that the information provided is true and accurate to the best of my knowledge. I acknowledge that my electronic signature constitutes formal authentication of this declaration
C5: TRUE | D5: =IF(Setup!B9="","","I, "&Setup!B9&"confirm that program coordinator "&Setup!B10&"has verifed and approved the course plan for electronic signature") -> I, Dr. Devi Prasad Mconfirm that program coordinator Dr. Sathyendranath Malli has verifed and approved the course plan for electronic signature
